; magic number 0xCAFEBABE
; bytecode version 45.3

; constant pool count 112
; cp[1] (offset 0xf) -> CONSTANT_NameAndType 44, 104
; cp[2] (offset 0x14) -> CONSTANT_Fieldref 85, 15
; cp[3] (offset 0x21) -> CONSTANT_Utf8 "SourceFile"
; cp[4] (offset 0x26) -> CONSTANT_NameAndType 14, 34
; cp[5] (offset 0x38) -> CONSTANT_Utf8 "()LCustomPoint;"
; cp[6] (offset 0x41) -> CONSTANT_Utf8 "<init>"
; cp[7] (offset 0x4c) -> CONSTANT_Utf8 "getHeros"
; cp[8] (offset 0x51) -> CONSTANT_Methodref 23, 92
; cp[9] (offset 0x56) -> CONSTANT_NameAndType 18, 97
; cp[10] (offset 0x6d) -> CONSTANT_Utf8 "()Ljava/lang/String;"
; cp[11] (offset 0x72) -> CONSTANT_NameAndType 100, 104
; cp[12] (offset 0x7a) -> CONSTANT_Utf8 "print"
; cp[13] (offset 0x7f) -> CONSTANT_NameAndType 26, 81
; cp[14] (offset 0x89) -> CONSTANT_Utf8 "println"
; cp[15] (offset 0x8e) -> CONSTANT_NameAndType 32, 110
; cp[16] (offset 0x93) -> CONSTANT_Methodref 80, 1
; cp[17] (offset 0x98) -> CONSTANT_Methodref 86, 51
; cp[18] (offset 0xa1) -> CONSTANT_Utf8 "output"
; cp[19] (offset 0xa6) -> CONSTANT_NameAndType 40, 104
; cp[20] (offset 0xab) -> CONSTANT_NameAndType 12, 34
; cp[21] (offset 0xb0) -> CONSTANT_Methodref 103, 20
; cp[22] (offset 0xb5) -> CONSTANT_NameAndType 109, 50
; cp[23] (offset 0xb8) -> CONSTANT_Class 45
; cp[24] (offset 0xbd) -> CONSTANT_Methodref 86, 66
; cp[25] (offset 0xc2) -> CONSTANT_NameAndType 82, 104
; cp[26] (offset 0xc9) -> CONSTANT_Utf8 "getY"
; cp[27] (offset 0xd0) -> CONSTANT_Utf8 "getX"
; cp[28] (offset 0xd5) -> CONSTANT_NameAndType 7, 104
; cp[29] (offset 0xd8) -> CONSTANT_String 38
; cp[30] (offset 0xdd) -> CONSTANT_NameAndType 47, 5
; cp[31] (offset 0xf5) -> CONSTANT_Utf8 "(Ljava/lang/Object;)V"
; cp[32] (offset 0xfd) -> CONSTANT_Utf8 "infos"
; cp[33] (offset 0x102) -> CONSTANT_Methodref 85, 22
; cp[34] (offset 0x11a) -> CONSTANT_Utf8 "(Ljava/lang/String;)V"
; cp[35] (offset 0x11f) -> CONSTANT_Methodref 80, 25
; cp[36] (offset 0x12b) -> CONSTANT_Utf8 "Dungeon.j"
; cp[37] (offset 0x135) -> CONSTANT_Utf8 "Dungeon"
; cp[38] (offset 0x139) -> CONSTANT_Utf8 "|"
; cp[39] (offset 0x13e) -> CONSTANT_Methodref 85, 48
; cp[40] (offset 0x14c) -> CONSTANT_Utf8 "getUpstairs"
; cp[41] (offset 0x151) -> CONSTANT_NameAndType 57, 31
; cp[42] (offset 0x158) -> CONSTANT_Utf8 "size"
; cp[43] (offset 0x15d) -> CONSTANT_Methodref 103, 102
; cp[44] (offset 0x16c) -> CONSTANT_Utf8 "getTreasures"
; cp[45] (offset 0x17f) -> CONSTANT_Utf8 "java/lang/Object"
; cp[46] (offset 0x184) -> CONSTANT_Methodref 88, 13
; cp[47] (offset 0x193) -> CONSTANT_Utf8 "getDimension"
; cp[48] (offset 0x198) -> CONSTANT_NameAndType 90, 70
; cp[49] (offset 0x19d) -> CONSTANT_Methodref 86, 102
; cp[50] (offset 0x1c2) -> CONSTANT_Utf8 "(Ljava/lang/String;LCustomPoint;)V"
; cp[51] (offset 0x1c7) -> CONSTANT_NameAndType 42, 81
; cp[52] (offset 0x1ca) -> CONSTANT_String 61
; cp[53] (offset 0x1cd) -> CONSTANT_String 62
; cp[54] (offset 0x1dc) -> CONSTANT_Utf8 "setElementAt"
; cp[55] (offset 0x1e3) -> CONSTANT_Utf8 "Code"
; cp[56] (offset 0x1e6) -> CONSTANT_String 64
; cp[57] (offset 0x1f3) -> CONSTANT_Utf8 "addElement"
; cp[58] (offset 0x1f6) -> CONSTANT_String 68
; cp[59] (offset 0x20e) -> CONSTANT_Utf8 "(I)Ljava/lang/Object;"
; cp[60] (offset 0x211) -> CONSTANT_String 71
; cp[61] (offset 0x215) -> CONSTANT_Utf8 "U"
; cp[62] (offset 0x219) -> CONSTANT_Utf8 "T"
; cp[63] (offset 0x232) -> CONSTANT_Utf8 "(Ljava/lang/Object;I)V"
; cp[64] (offset 0x236) -> CONSTANT_Utf8 "M"
; cp[65] (offset 0x23b) -> CONSTANT_Methodref 80, 19
; cp[66] (offset 0x240) -> CONSTANT_NameAndType 96, 59
; cp[67] (offset 0x245) -> CONSTANT_Methodref 103, 4
; cp[68] (offset 0x249) -> CONSTANT_Utf8 "H"
; cp[69] (offset 0x24e) -> CONSTANT_Methodref 80, 28
; cp[70] (offset 0x254) -> CONSTANT_Utf8 "()V"
; cp[71] (offset 0x258) -> CONSTANT_Utf8 "D"
; cp[72] (offset 0x25f) -> CONSTANT_Utf8 "draw"
; cp[73] (offset 0x262) -> CONSTANT_String 91
; cp[74] (offset 0x26d) -> CONSTANT_Utf8 "toString"
; cp[75] (offset 0x27b) -> CONSTANT_Utf8 "CustomPoint"
; cp[76] (offset 0x27e) -> CONSTANT_String 93
; cp[77] (offset 0x283) -> CONSTANT_Fieldref 85, 9
; cp[78] (offset 0x288) -> CONSTANT_Methodref 86, 89
; cp[79] (offset 0x28d) -> CONSTANT_Methodref 80, 11
; cp[80] (offset 0x290) -> CONSTANT_Class 84
; cp[81] (offset 0x296) -> CONSTANT_Utf8 "()I"
; cp[82] (offset 0x2a6) -> CONSTANT_Utf8 "getDownstairs"
; cp[83] (offset 0x2ab) -> CONSTANT_NameAndType 27, 81
; cp[84] (offset 0x2ba) -> CONSTANT_Utf8 "DungeonInfos"
; cp[85] (offset 0x2bd) -> CONSTANT_Class 37
; cp[86] (offset 0x2c0) -> CONSTANT_Class 98
; cp[87] (offset 0x2c3) -> CONSTANT_String 99
; cp[88] (offset 0x2c6) -> CONSTANT_Class 75
; cp[89] (offset 0x2cb) -> CONSTANT_NameAndType 54, 63
; cp[90] (offset 0x2d8) -> CONSTANT_Utf8 "createRoom"
; cp[91] (offset 0x2dc) -> CONSTANT_Utf8 "-"
; cp[92] (offset 0x2e1) -> CONSTANT_NameAndType 74, 10
; cp[93] (offset 0x2e5) -> CONSTANT_Utf8 "+"
; cp[94] (offset 0x2ea) -> CONSTANT_Methodref 86, 41
; cp[95] (offset 0x2fc) -> CONSTANT_Utf8 "joos/lib/JoosIO"
; cp[96] (offset 0x308) -> CONSTANT_Utf8 "elementAt"
; cp[97] (offset 0x31d) -> CONSTANT_Utf8 "Ljava/util/Vector;"
; cp[98] (offset 0x330) -> CONSTANT_Utf8 "java/util/Vector"
; cp[99] (offset 0x334) -> CONSTANT_Utf8 " "
; cp[100] (offset 0x342) -> CONSTANT_Utf8 "getMonsters"
; cp[101] (offset 0x356) -> CONSTANT_Utf8 "(LDungeonInfos;)V"
; cp[102] (offset 0x35b) -> CONSTANT_NameAndType 6, 70
; cp[103] (offset 0x35e) -> CONSTANT_Class 95
; cp[104] (offset 0x375) -> CONSTANT_Utf8 "()Ljava/util/Vector;"
; cp[105] (offset 0x37a) -> CONSTANT_Methodref 88, 83
; cp[106] (offset 0x37f) -> CONSTANT_Methodref 80, 30
; cp[107] (offset 0x382) -> CONSTANT_String 111
; cp[108] (offset 0x387) -> CONSTANT_Methodref 23, 102
; cp[109] (offset 0x394) -> CONSTANT_Utf8 "createItem"
; cp[110] (offset 0x3a5) -> CONSTANT_Utf8 "LDungeonInfos;"
; cp[111] (offset 0x3a8) -> CONSTANT_Utf8 ""

; access flags = 0x21 [ ACC_SUPER ACC_PUBLIC ]
; this_class index = 85
; super_class index = 23

; interfaces_count = 0


; fields_count = 2

; fields[0] (offset 0x3b2) :
;     access_flags 0x4 [ ACC_PROTECTED ]
;     name_index 32 (infos)
;     descriptor_index 110 (LDungeonInfos;)
;     attributes_count 0

; fields[1] (offset 0x3ba) :
;     access_flags 0x4 [ ACC_PROTECTED ]
;     name_index 18 (output)
;     descriptor_index 97 (Ljava/util/Vector;)
;     attributes_count 0

; methods_count 4

; methods[0] (offset 0x3c4) :
;     access_flags 0x1 [ ACC_PUBLIC ]
;     name_index 6 (<init>)
;     descriptor_index 101 ((LDungeonInfos;)V)
;     attributes_count 1
;     method_attributes[0] :
;         name_index 55 (Code)
;         attribute_length 39
;         max_stack 3
;         max_locals 2
;         code_length 27
;         code :
;                0: aload_0 
;                1: invokespecial 108 (java/lang/Object/<init> ()V) 
;                4: aload_1 
;                5: dup 
;                6: aload_0 
;                7: swap 
;                8: putfield 2 (Dungeon/infos LDungeonInfos;) 
;               11: pop 
;               12: new 86 (java/util/Vector) 
;               15: dup 
;               16: invokespecial 49 (java/util/Vector/<init> ()V) 
;               19: dup 
;               20: aload_0 
;               21: swap 
;               22: putfield 77 (Dungeon/output Ljava/util/Vector;) 
;               25: pop 
;               26: return 
;         exception_table_length 0
;         attributes_count 0


; methods[1] (offset 0x3f9) :
;     access_flags 0x1 [ ACC_PUBLIC ]
;     name_index 72 (draw)
;     descriptor_index 70 (()V)
;     attributes_count 1
;     method_attributes[0] :
;         name_index 55 (Code)
;         attribute_length 410
;         max_stack 4
;         max_locals 6
;         code_length 398
;         code :
;                0: aload_0 
;                1: invokevirtual 39 (Dungeon/createRoom ()V) 
;                4: aload_0 
;                5: getfield 2 (Dungeon/infos LDungeonInfos;) 
;                8: invokevirtual 79 (DungeonInfos/getMonsters ()Ljava/util/Vector;) 
;               11: dup 
;               12: astore 5 
;               14: pop 
;               15: iconst_0 
;               16: dup 
;               17: istore_2 
;               18: pop 
;               19: iload_2 
;               20: aload 5 
;               22: invokevirtual 17 (java/util/Vector/size ()I) 
;               25: if_icmplt 7 
;               28: iconst_0 
;               29: goto 4 
;               32: iconst_1 
;               33: ifeq 27 
;               36: aload_0 
;               37: ldc 56 ("M") 
;               39: aload 5 
;               41: iload_2 
;               42: invokevirtual 24 (java/util/Vector/elementAt (I)Ljava/lang/Object;) 
;               45: checkcast 88 (CustomPoint) 
;               48: invokevirtual 33 (Dungeon/createItem (Ljava/lang/String;LCustomPoint;)V) 
;               51: iload_2 
;               52: iconst_1 
;               53: iadd 
;               54: dup 
;               55: istore_2 
;               56: pop 
;               57: goto -38 
;               60: aload_0 
;               61: getfield 2 (Dungeon/infos LDungeonInfos;) 
;               64: invokevirtual 65 (DungeonInfos/getUpstairs ()Ljava/util/Vector;) 
;               67: dup 
;               68: astore 5 
;               70: pop 
;               71: iconst_0 
;               72: dup 
;               73: istore_2 
;               74: pop 
;               75: iload_2 
;               76: aload 5 
;               78: invokevirtual 17 (java/util/Vector/size ()I) 
;               81: if_icmplt 7 
;               84: iconst_0 
;               85: goto 4 
;               88: iconst_1 
;               89: ifeq 27 
;               92: aload_0 
;               93: ldc 52 ("U") 
;               95: aload 5 
;               97: iload_2 
;               98: invokevirtual 24 (java/util/Vector/elementAt (I)Ljava/lang/Object;) 
;              101: checkcast 88 (CustomPoint) 
;              104: invokevirtual 33 (Dungeon/createItem (Ljava/lang/String;LCustomPoint;)V) 
;              107: iload_2 
;              108: iconst_1 
;              109: iadd 
;              110: dup 
;              111: istore_2 
;              112: pop 
;              113: goto -38 
;              116: aload_0 
;              117: getfield 2 (Dungeon/infos LDungeonInfos;) 
;              120: invokevirtual 35 (DungeonInfos/getDownstairs ()Ljava/util/Vector;) 
;              123: dup 
;              124: astore 5 
;              126: pop 
;              127: iconst_0 
;              128: dup 
;              129: istore_2 
;              130: pop 
;              131: iload_2 
;              132: aload 5 
;              134: invokevirtual 17 (java/util/Vector/size ()I) 
;              137: if_icmplt 7 
;              140: iconst_0 
;              141: goto 4 
;              144: iconst_1 
;              145: ifeq 27 
;              148: aload_0 
;              149: ldc 60 ("D") 
;              151: aload 5 
;              153: iload_2 
;              154: invokevirtual 24 (java/util/Vector/elementAt (I)Ljava/lang/Object;) 
;              157: checkcast 88 (CustomPoint) 
;              160: invokevirtual 33 (Dungeon/createItem (Ljava/lang/String;LCustomPoint;)V) 
;              163: iload_2 
;              164: iconst_1 
;              165: iadd 
;              166: dup 
;              167: istore_2 
;              168: pop 
;              169: goto -38 
;              172: aload_0 
;              173: getfield 2 (Dungeon/infos LDungeonInfos;) 
;              176: invokevirtual 16 (DungeonInfos/getTreasures ()Ljava/util/Vector;) 
;              179: dup 
;              180: astore 5 
;              182: pop 
;              183: iconst_0 
;              184: dup 
;              185: istore_2 
;              186: pop 
;              187: iload_2 
;              188: aload 5 
;              190: invokevirtual 17 (java/util/Vector/size ()I) 
;              193: if_icmplt 7 
;              196: iconst_0 
;              197: goto 4 
;              200: iconst_1 
;              201: ifeq 27 
;              204: aload_0 
;              205: ldc 53 ("T") 
;              207: aload 5 
;              209: iload_2 
;              210: invokevirtual 24 (java/util/Vector/elementAt (I)Ljava/lang/Object;) 
;              213: checkcast 88 (CustomPoint) 
;              216: invokevirtual 33 (Dungeon/createItem (Ljava/lang/String;LCustomPoint;)V) 
;              219: iload_2 
;              220: iconst_1 
;              221: iadd 
;              222: dup 
;              223: istore_2 
;              224: pop 
;              225: goto -38 
;              228: aload_0 
;              229: getfield 2 (Dungeon/infos LDungeonInfos;) 
;              232: invokevirtual 69 (DungeonInfos/getHeros ()Ljava/util/Vector;) 
;              235: dup 
;              236: astore 5 
;              238: pop 
;              239: iconst_0 
;              240: dup 
;              241: istore_2 
;              242: pop 
;              243: iload_2 
;              244: aload 5 
;              246: invokevirtual 17 (java/util/Vector/size ()I) 
;              249: if_icmplt 7 
;              252: iconst_0 
;              253: goto 4 
;              256: iconst_1 
;              257: ifeq 27 
;              260: aload_0 
;              261: ldc 58 ("H") 
;              263: aload 5 
;              265: iload_2 
;              266: invokevirtual 24 (java/util/Vector/elementAt (I)Ljava/lang/Object;) 
;              269: checkcast 88 (CustomPoint) 
;              272: invokevirtual 33 (Dungeon/createItem (Ljava/lang/String;LCustomPoint;)V) 
;              275: iload_2 
;              276: iconst_1 
;              277: iadd 
;              278: dup 
;              279: istore_2 
;              280: pop 
;              281: goto -38 
;              284: new 103 (joos/lib/JoosIO) 
;              287: dup 
;              288: invokespecial 43 (joos/lib/JoosIO/<init> ()V) 
;              291: dup 
;              292: astore_1 
;              293: pop 
;              294: aload_0 
;              295: getfield 2 (Dungeon/infos LDungeonInfos;) 
;              298: invokevirtual 106 (DungeonInfos/getDimension ()LCustomPoint;) 
;              301: dup 
;              302: astore 4 
;              304: pop 
;              305: iconst_0 
;              306: dup 
;              307: istore_2 
;              308: pop 
;              309: iload_2 
;              310: aload 4 
;              312: invokevirtual 46 (CustomPoint/getY ()I) 
;              315: iconst_2 
;              316: iadd 
;              317: if_icmplt 7 
;              320: iconst_0 
;              321: goto 4 
;              324: iconst_1 
;              325: ifeq 72 
;              328: iconst_0 
;              329: dup 
;              330: istore_3 
;              331: pop 
;              332: iload_3 
;              333: aload 4 
;              335: invokevirtual 105 (CustomPoint/getX ()I) 
;              338: iconst_2 
;              339: iadd 
;              340: if_icmplt 7 
;              343: iconst_0 
;              344: goto 4 
;              347: iconst_1 
;              348: ifeq 34 
;              351: aload_1 
;              352: aload_0 
;              353: getfield 77 (Dungeon/output Ljava/util/Vector;) 
;              356: iload_2 
;              357: invokevirtual 24 (java/util/Vector/elementAt (I)Ljava/lang/Object;) 
;              360: checkcast 86 (java/util/Vector) 
;              363: iload_3 
;              364: invokevirtual 24 (java/util/Vector/elementAt (I)Ljava/lang/Object;) 
;              367: invokevirtual 8 (java/lang/Object/toString ()Ljava/lang/String;) 
;              370: invokevirtual 21 (joos/lib/JoosIO/print (Ljava/lang/String;)V) 
;              373: iload_3 
;              374: iconst_1 
;              375: iadd 
;              376: dup 
;              377: istore_3 
;              378: pop 
;              379: goto -47 
;              382: aload_1 
;              383: ldc 107 ("") 
;              385: invokevirtual 67 (joos/lib/JoosIO/println (Ljava/lang/String;)V) 
;              388: iload_2 
;              389: iconst_1 
;              390: iadd 
;              391: dup 
;              392: istore_2 
;              393: pop 
;              394: goto -85 
;              397: return 
;         exception_table_length 0
;         attributes_count 0


; methods[2] (offset 0x5a1) :
;     access_flags 0x1 [ ACC_PUBLIC ]
;     name_index 90 (createRoom)
;     descriptor_index 70 (()V)
;     attributes_count 1
;     method_attributes[0] :
;         name_index 55 (Code)
;         attribute_length 346
;         max_stack 3
;         max_locals 5
;         code_length 334
;         code :
;                0: aload_0 
;                1: getfield 2 (Dungeon/infos LDungeonInfos;) 
;                4: invokevirtual 106 (DungeonInfos/getDimension ()LCustomPoint;) 
;                7: dup 
;                8: astore_3 
;                9: pop 
;               10: iconst_0 
;               11: dup 
;               12: istore_1 
;               13: pop 
;               14: iload_1 
;               15: aload_3 
;               16: invokevirtual 46 (CustomPoint/getY ()I) 
;               19: iconst_2 
;               20: iadd 
;               21: if_icmplt 7 
;               24: iconst_0 
;               25: goto 4 
;               28: iconst_1 
;               29: ifeq 304 
;               32: new 86 (java/util/Vector) 
;               35: dup 
;               36: invokespecial 49 (java/util/Vector/<init> ()V) 
;               39: dup 
;               40: astore 4 
;               42: pop 
;               43: iconst_0 
;               44: dup 
;               45: istore_2 
;               46: pop 
;               47: iload_2 
;               48: aload_3 
;               49: invokevirtual 105 (CustomPoint/getX ()I) 
;               52: iconst_2 
;               53: iadd 
;               54: if_icmplt 7 
;               57: iconst_0 
;               58: goto 4 
;               61: iconst_1 
;               62: ifeq 253 
;               65: iload_1 
;               66: iconst_0 
;               67: if_icmpeq 7 
;               70: iconst_0 
;               71: goto 4 
;               74: iconst_1 
;               75: dup 
;               76: ifeq 14 
;               79: pop 
;               80: iload_2 
;               81: iconst_0 
;               82: if_icmpeq 7 
;               85: iconst_0 
;               86: goto 4 
;               89: iconst_1 
;               90: dup 
;               91: ifne 34 
;               94: pop 
;               95: iload_1 
;               96: aload_3 
;               97: invokevirtual 46 (CustomPoint/getY ()I) 
;              100: iconst_1 
;              101: iadd 
;              102: if_icmpeq 7 
;              105: iconst_0 
;              106: goto 4 
;              109: iconst_1 
;              110: dup 
;              111: ifeq 14 
;              114: pop 
;              115: iload_2 
;              116: iconst_0 
;              117: if_icmpeq 7 
;              120: iconst_0 
;              121: goto 4 
;              124: iconst_1 
;              125: dup 
;              126: ifne 34 
;              129: pop 
;              130: iload_1 
;              131: iconst_0 
;              132: if_icmpeq 7 
;              135: iconst_0 
;              136: goto 4 
;              139: iconst_1 
;              140: dup 
;              141: ifeq 19 
;              144: pop 
;              145: iload_2 
;              146: aload_3 
;              147: invokevirtual 105 (CustomPoint/getX ()I) 
;              150: iconst_1 
;              151: iadd 
;              152: if_icmpeq 7 
;              155: iconst_0 
;              156: goto 4 
;              159: iconst_1 
;              160: dup 
;              161: ifne 39 
;              164: pop 
;              165: iload_1 
;              166: aload_3 
;              167: invokevirtual 46 (CustomPoint/getY ()I) 
;              170: iconst_1 
;              171: iadd 
;              172: if_icmpeq 7 
;              175: iconst_0 
;              176: goto 4 
;              179: iconst_1 
;              180: dup 
;              181: ifeq 19 
;              184: pop 
;              185: iload_2 
;              186: aload_3 
;              187: invokevirtual 105 (CustomPoint/getX ()I) 
;              190: iconst_1 
;              191: iadd 
;              192: if_icmpeq 7 
;              195: iconst_0 
;              196: goto 4 
;              199: iconst_1 
;              200: ifeq 13 
;              203: aload 4 
;              205: ldc 76 ("+") 
;              207: invokevirtual 94 (java/util/Vector/addElement (Ljava/lang/Object;)V) 
;              210: goto 96 
;              213: iload_1 
;              214: iconst_0 
;              215: if_icmpeq 7 
;              218: iconst_0 
;              219: goto 4 
;              222: iconst_1 
;              223: dup 
;              224: ifne 19 
;              227: pop 
;              228: iload_1 
;              229: aload_3 
;              230: invokevirtual 46 (CustomPoint/getY ()I) 
;              233: iconst_1 
;              234: iadd 
;              235: if_icmpeq 7 
;              238: iconst_0 
;              239: goto 4 
;              242: iconst_1 
;              243: ifeq 13 
;              246: aload 4 
;              248: ldc 73 ("-") 
;              250: invokevirtual 94 (java/util/Vector/addElement (Ljava/lang/Object;)V) 
;              253: goto 53 
;              256: iload_2 
;              257: iconst_0 
;              258: if_icmpeq 7 
;              261: iconst_0 
;              262: goto 4 
;              265: iconst_1 
;              266: dup 
;              267: ifne 19 
;              270: pop 
;              271: iload_2 
;              272: aload_3 
;              273: invokevirtual 105 (CustomPoint/getX ()I) 
;              276: iconst_1 
;              277: iadd 
;              278: if_icmpeq 7 
;              281: iconst_0 
;              282: goto 4 
;              285: iconst_1 
;              286: ifeq 13 
;              289: aload 4 
;              291: ldc 29 ("|") 
;              293: invokevirtual 94 (java/util/Vector/addElement (Ljava/lang/Object;)V) 
;              296: goto 10 
;              299: aload 4 
;              301: ldc 87 (" ") 
;              303: invokevirtual 94 (java/util/Vector/addElement (Ljava/lang/Object;)V) 
;              306: iload_2 
;              307: iconst_1 
;              308: iadd 
;              309: dup 
;              310: istore_2 
;              311: pop 
;              312: goto -265 
;              315: aload_0 
;              316: getfield 77 (Dungeon/output Ljava/util/Vector;) 
;              319: aload 4 
;              321: invokevirtual 94 (java/util/Vector/addElement (Ljava/lang/Object;)V) 
;              324: iload_1 
;              325: iconst_1 
;              326: iadd 
;              327: dup 
;              328: istore_1 
;              329: pop 
;              330: goto -316 
;              333: return 
;         exception_table_length 0
;         attributes_count 0


; methods[3] (offset 0x709) :
;     access_flags 0x1 [ ACC_PUBLIC ]
;     name_index 109 (createItem)
;     descriptor_index 50 ((Ljava/lang/String;LCustomPoint;)V)
;     attributes_count 1
;     method_attributes[0] :
;         name_index 55 (Code)
;         attribute_length 39
;         max_stack 3
;         max_locals 4
;         code_length 27
;         code :
;                0: aload_0 
;                1: getfield 77 (Dungeon/output Ljava/util/Vector;) 
;                4: aload_2 
;                5: invokevirtual 46 (CustomPoint/getY ()I) 
;                8: invokevirtual 24 (java/util/Vector/elementAt (I)Ljava/lang/Object;) 
;               11: checkcast 86 (java/util/Vector) 
;               14: dup 
;               15: astore_3 
;               16: pop 
;               17: aload_3 
;               18: aload_1 
;               19: aload_2 
;               20: invokevirtual 105 (CustomPoint/getX ()I) 
;               23: invokevirtual 78 (java/util/Vector/setElementAt (Ljava/lang/Object;I)V) 
;               26: return 
;         exception_table_length 0
;         attributes_count 0



; attributes_count 1

; class_attributes[0] (offset 0x740) :
;     name_index 3 (SourceFile)
;     attribute_length 2
;     sourcefile_index 36

; End of file reached successfully. Enjoy :)
