; magic number 0xCAFEBABE
; bytecode version 45.3

; constant pool count 108
; cp[1] (offset 0xf) -> CONSTANT_NameAndType 21, 62
; cp[2] (offset 0x24) -> CONSTANT_Utf8 "Ljava/lang/String;"
; cp[3] (offset 0x27) -> CONSTANT_String 105
; cp[4] (offset 0x2a) -> CONSTANT_String 78
; cp[5] (offset 0x37) -> CONSTANT_Utf8 "SourceFile"
; cp[6] (offset 0x3c) -> CONSTANT_Methodref 90, 98
; cp[7] (offset 0x41) -> CONSTANT_NameAndType 19, 30
; cp[8] (offset 0x4a) -> CONSTANT_Utf8 "<init>"
; cp[9] (offset 0x4f) -> CONSTANT_Methodref 90, 49
; cp[10] (offset 0x58) -> CONSTANT_Utf8 "length"
; cp[11] (offset 0x5b) -> CONSTANT_String 41
; cp[12] (offset 0x5e) -> CONSTANT_String 33
; cp[13] (offset 0x63) -> CONSTANT_Methodref 48, 95
; cp[14] (offset 0x6a) -> CONSTANT_Utf8 "null"
; cp[15] (offset 0x77) -> CONSTANT_Utf8 "startsWith"
; cp[16] (offset 0x7c) -> CONSTANT_NameAndType 25, 30
; cp[17] (offset 0x90) -> CONSTANT_Utf8 "Ljoos/lib/JoosIO;"
; cp[18] (offset 0x95) -> CONSTANT_NameAndType 39, 80
; cp[19] (offset 0x9f) -> CONSTANT_Utf8 "println"
; cp[20] (offset 0xa4) -> CONSTANT_NameAndType 101, 87
; cp[21] (offset 0xb1) -> CONSTANT_Utf8 "ioImported"
; cp[22] (offset 0xb6) -> CONSTANT_NameAndType 78, 30
; cp[23] (offset 0xbb) -> CONSTANT_Fieldref 75, 53
; cp[24] (offset 0xbe) -> CONSTANT_Class 47
; cp[25] (offset 0xc8) -> CONSTANT_Utf8 "visible"
; cp[26] (offset 0xcf) -> CONSTANT_Utf8 "exit"
; cp[27] (offset 0xe7) -> CONSTANT_Utf8 "(Ljava/lang/Object;)Z"
; cp[28] (offset 0xec) -> CONSTANT_Integer 9
; cp[29] (offset 0xef) -> CONSTANT_String 44
; cp[30] (offset 0x107) -> CONSTANT_Utf8 "(Ljava/lang/String;)V"
; cp[31] (offset 0x120) -> CONSTANT_Utf8 "(Ljava/lang/String;I)Z"
; cp[32] (offset 0x125) -> CONSTANT_Methodref 75, 92
; cp[33] (offset 0x13f) -> CONSTANT_Utf8 "' can not be recognized"
; cp[34] (offset 0x14f) -> CONSTANT_Utf8 "Interpretor.j"
; cp[35] (offset 0x172) -> CONSTANT_Utf8 "Only module 'STDIO' is supported"
; cp[36] (offset 0x175) -> CONSTANT_String 100
; cp[37] (offset 0x17e) -> CONSTANT_Utf8 "equals"
; cp[38] (offset 0x183) -> CONSTANT_NameAndType 101, 54
; cp[39] (offset 0x18f) -> CONSTANT_Utf8 "substring"
; cp[40] (offset 0x194) -> CONSTANT_NameAndType 37, 27
; cp[41] (offset 0x1a5) -> CONSTANT_Utf8 "CAN HAS STDIO?"
; cp[42] (offset 0x1aa) -> CONSTANT_Methodref 75, 51
; cp[43] (offset 0x1af) -> CONSTANT_Methodref 75, 22
; cp[44] (offset 0x1b9) -> CONSTANT_Utf8 "running"
; cp[45] (offset 0x1be) -> CONSTANT_Methodref 90, 69
; cp[46] (offset 0x1c3) -> CONSTANT_Methodref 96, 95
; cp[47] (offset 0x1d6) -> CONSTANT_Utf8 "java/lang/Object"
; cp[48] (offset 0x1d9) -> CONSTANT_Class 61
; cp[49] (offset 0x1de) -> CONSTANT_NameAndType 10, 82
; cp[50] (offset 0x1ea) -> CONSTANT_Utf8 "interpret"
; cp[51] (offset 0x1ef) -> CONSTANT_NameAndType 63, 30
; cp[52] (offset 0x1f2) -> CONSTANT_String 66
; cp[53] (offset 0x1f7) -> CONSTANT_NameAndType 106, 2
; cp[54] (offset 0x20d) -> CONSTANT_Utf8 "LStringEscapeUtils;"
; cp[55] (offset 0x211) -> CONSTANT_Utf8 "f"
; cp[56] (offset 0x216) -> CONSTANT_NameAndType 55, 17
; cp[57] (offset 0x21b) -> CONSTANT_Fieldref 75, 56
; cp[58] (offset 0x220) -> CONSTANT_Methodref 75, 16
; cp[59] (offset 0x227) -> CONSTANT_Utf8 "Code"
; cp[60] (offset 0x22a) -> CONSTANT_String 14
; cp[61] (offset 0x23e) -> CONSTANT_Utf8 "StringEscapeUtils"
; cp[62] (offset 0x242) -> CONSTANT_Utf8 "Z"
; cp[63] (offset 0x24c) -> CONSTANT_Utf8 "openMod"
; cp[64] (offset 0x256) -> CONSTANT_Utf8 "KTHXBYE"
; cp[65] (offset 0x259) -> CONSTANT_String 64
; cp[66] (offset 0x263) -> CONSTANT_Utf8 "VISIBLE"
; cp[67] (offset 0x271) -> CONSTANT_Utf8 "Interpretor"
; cp[68] (offset 0x291) -> CONSTANT_Utf8 "Program must start with 'HAI'"
; cp[69] (offset 0x296) -> CONSTANT_NameAndType 103, 87
; cp[70] (offset 0x29b) -> CONSTANT_Methodref 90, 40
; cp[71] (offset 0x2a0) -> CONSTANT_Methodref 90, 18
; cp[72] (offset 0x2a3) -> CONSTANT_String 35
; cp[73] (offset 0x2a8) -> CONSTANT_Fieldref 75, 38
; cp[74] (offset 0x2ad) -> CONSTANT_Methodref 96, 7
; cp[75] (offset 0x2b0) -> CONSTANT_Class 67
; cp[76] (offset 0x2b3) -> CONSTANT_String 26
; cp[77] (offset 0x2b9) -> CONSTANT_Utf8 "()V"
; cp[78] (offset 0x2c0) -> CONSTANT_Utf8 "init"
; cp[79] (offset 0x2ca) -> CONSTANT_Utf8 "crashed"
; cp[80] (offset 0x2e3) -> CONSTANT_Utf8 "(II)Ljava/lang/String;"
; cp[81] (offset 0x2e6) -> CONSTANT_String 68
; cp[82] (offset 0x2ec) -> CONSTANT_Utf8 "()I"
; cp[83] (offset 0x2ef) -> CONSTANT_String 88
; cp[84] (offset 0x2f4) -> CONSTANT_NameAndType 79, 30
; cp[85] (offset 0x2f9) -> CONSTANT_NameAndType 94, 30
; cp[86] (offset 0x2fe) -> CONSTANT_Methodref 75, 85
; cp[87] (offset 0x327) -> CONSTANT_Utf8 "(Ljava/lang/String;)Ljava/lang/String;"
; cp[88] (offset 0x32b) -> CONSTANT_Utf8 "'"
; cp[89] (offset 0x33d) -> CONSTANT_Utf8 "joos/lib/JoosIO"
; cp[90] (offset 0x340) -> CONSTANT_Class 99
; cp[91] (offset 0x346) -> CONSTANT_Utf8 "HAI"
; cp[92] (offset 0x34b) -> CONSTANT_NameAndType 26, 77
; cp[93] (offset 0x350) -> CONSTANT_Methodref 75, 84
; cp[94] (offset 0x356) -> CONSTANT_Utf8 "run"
; cp[95] (offset 0x35b) -> CONSTANT_NameAndType 8, 77
; cp[96] (offset 0x35e) -> CONSTANT_Class 89
; cp[97] (offset 0x363) -> CONSTANT_Methodref 48, 20
; cp[98] (offset 0x368) -> CONSTANT_NameAndType 15, 31
; cp[99] (offset 0x37b) -> CONSTANT_Utf8 "java/lang/String"
; cp[100] (offset 0x3a4) -> CONSTANT_Utf8 "Can not execute VISIBLE with out stdio"
; cp[101] (offset 0x3ad) -> CONSTANT_Utf8 "escape"
; cp[102] (offset 0x3b0) -> CONSTANT_String 91
; cp[103] (offset 0x3b9) -> CONSTANT_Utf8 "concat"
; cp[104] (offset 0x3be) -> CONSTANT_Fieldref 75, 1
; cp[105] (offset 0x3c4) -> CONSTANT_Utf8 "CAN"
; cp[106] (offset 0x3cc) -> CONSTANT_Utf8 "state"
; cp[107] (offset 0x3d1) -> CONSTANT_Methodref 24, 95

; access flags = 0x21 [ ACC_SUPER ACC_PUBLIC ]
; this_class index = 75
; super_class index = 24

; interfaces_count = 0


; fields_count = 4

; fields[0] (offset 0x3db) :
;     access_flags 0x4 [ ACC_PROTECTED ]
;     name_index 106 (state)
;     descriptor_index 2 (Ljava/lang/String;)
;     attributes_count 0

; fields[1] (offset 0x3e3) :
;     access_flags 0x4 [ ACC_PROTECTED ]
;     name_index 55 (f)
;     descriptor_index 17 (Ljoos/lib/JoosIO;)
;     attributes_count 0

; fields[2] (offset 0x3eb) :
;     access_flags 0x4 [ ACC_PROTECTED ]
;     name_index 21 (ioImported)
;     descriptor_index 62 (Z)
;     attributes_count 0

; fields[3] (offset 0x3f3) :
;     access_flags 0x4 [ ACC_PROTECTED ]
;     name_index 101 (escape)
;     descriptor_index 54 (LStringEscapeUtils;)
;     attributes_count 0

; methods_count 8

; methods[0] (offset 0x3fd) :
;     access_flags 0x1 [ ACC_PUBLIC ]
;     name_index 8 (<init>)
;     descriptor_index 77 (()V)
;     attributes_count 1
;     method_attributes[0] :
;         name_index 59 (Code)
;         attribute_length 62
;         max_stack 3
;         max_locals 1
;         code_length 50
;         code :
;                0: aload_0 
;                1: invokespecial 107 (java/lang/Object/<init> ()V) 
;                4: ldc 4 ("init") 
;                6: dup 
;                7: aload_0 
;                8: swap 
;                9: putfield 23 (Interpretor/state Ljava/lang/String;) 
;               12: pop 
;               13: new 96 (joos/lib/JoosIO) 
;               16: dup 
;               17: invokespecial 46 (joos/lib/JoosIO/<init> ()V) 
;               20: dup 
;               21: aload_0 
;               22: swap 
;               23: putfield 57 (Interpretor/f Ljoos/lib/JoosIO;) 
;               26: pop 
;               27: iconst_0 
;               28: dup 
;               29: aload_0 
;               30: swap 
;               31: putfield 104 (Interpretor/ioImported Z) 
;               34: pop 
;               35: new 48 (StringEscapeUtils) 
;               38: dup 
;               39: invokespecial 13 (StringEscapeUtils/<init> ()V) 
;               42: dup 
;               43: aload_0 
;               44: swap 
;               45: putfield 73 (Interpretor/escape LStringEscapeUtils;) 
;               48: pop 
;               49: return 
;         exception_table_length 0
;         attributes_count 0


; methods[1] (offset 0x449) :
;     access_flags 0x1 [ ACC_PUBLIC ]
;     name_index 50 (interpret)
;     descriptor_index 30 ((Ljava/lang/String;)V)
;     attributes_count 1
;     method_attributes[0] :
;         name_index 59 (Code)
;         attribute_length 50
;         max_stack 2
;         max_locals 2
;         code_length 38
;         code :
;                0: aload_0 
;                1: getfield 23 (Interpretor/state Ljava/lang/String;) 
;                4: ldc 4 ("init") 
;                6: invokevirtual 70 (java/lang/String/equals (Ljava/lang/Object;)Z) 
;                9: ifeq 11 
;               12: aload_0 
;               13: aload_1 
;               14: invokevirtual 43 (Interpretor/init (Ljava/lang/String;)V) 
;               17: goto 20 
;               20: aload_0 
;               21: getfield 23 (Interpretor/state Ljava/lang/String;) 
;               24: ldc 29 ("running") 
;               26: invokevirtual 70 (java/lang/String/equals (Ljava/lang/Object;)Z) 
;               29: ifeq 8 
;               32: aload_0 
;               33: aload_1 
;               34: invokevirtual 86 (Interpretor/run (Ljava/lang/String;)V) 
;               37: return 
;         exception_table_length 0
;         attributes_count 0


; methods[2] (offset 0x489) :
;     access_flags 0x1 [ ACC_PUBLIC ]
;     name_index 78 (init)
;     descriptor_index 30 ((Ljava/lang/String;)V)
;     attributes_count 1
;     method_attributes[0] :
;         name_index 59 (Code)
;         attribute_length 48
;         max_stack 3
;         max_locals 2
;         code_length 36
;         code :
;                0: aload_1 
;                1: ldc 102 ("HAI") 
;                3: invokevirtual 70 (java/lang/String/equals (Ljava/lang/Object;)Z) 
;                6: ifeq 7 
;                9: iconst_0 
;               10: goto 4 
;               13: iconst_1 
;               14: ifeq 12 
;               17: aload_0 
;               18: ldc 81 ("Program must start with 'HAI'") 
;               20: invokevirtual 93 (Interpretor/crashed (Ljava/lang/String;)V) 
;               23: goto 12 
;               26: ldc 29 ("running") 
;               28: dup 
;               29: aload_0 
;               30: swap 
;               31: putfield 23 (Interpretor/state Ljava/lang/String;) 
;               34: pop 
;               35: return 
;         exception_table_length 0
;         attributes_count 0


; methods[3] (offset 0x4c7) :
;     access_flags 0x1 [ ACC_PUBLIC ]
;     name_index 79 (crashed)
;     descriptor_index 30 ((Ljava/lang/String;)V)
;     attributes_count 1
;     method_attributes[0] :
;         name_index 59 (Code)
;         attribute_length 25
;         max_stack 2
;         max_locals 2
;         code_length 13
;         code :
;                0: aload_0 
;                1: invokevirtual 32 (Interpretor/exit ()V) 
;                4: aload_0 
;                5: getfield 57 (Interpretor/f Ljoos/lib/JoosIO;) 
;                8: aload_1 
;                9: invokevirtual 74 (joos/lib/JoosIO/println (Ljava/lang/String;)V) 
;               12: return 
;         exception_table_length 0
;         attributes_count 0


; methods[4] (offset 0x4ee) :
;     access_flags 0x1 [ ACC_PUBLIC ]
;     name_index 26 (exit)
;     descriptor_index 77 (()V)
;     attributes_count 1
;     method_attributes[0] :
;         name_index 59 (Code)
;         attribute_length 22
;         max_stack 3
;         max_locals 1
;         code_length 10
;         code :
;                0: ldc 76 ("exit") 
;                2: dup 
;                3: aload_0 
;                4: swap 
;                5: putfield 23 (Interpretor/state Ljava/lang/String;) 
;                8: pop 
;                9: return 
;         exception_table_length 0
;         attributes_count 0


; methods[5] (offset 0x512) :
;     access_flags 0x1 [ ACC_PUBLIC ]
;     name_index 94 (run)
;     descriptor_index 30 ((Ljava/lang/String;)V)
;     attributes_count 1
;     method_attributes[0] :
;         name_index 59 (Code)
;         attribute_length 120
;         max_stack 4
;         max_locals 2
;         code_length 108
;         code :
;                0: aload_1 
;                1: ldc 3 ("CAN") 
;                3: iconst_0 
;                4: invokevirtual 6 (java/lang/String/startsWith (Ljava/lang/String;I)Z) 
;                7: ifeq 11 
;               10: aload_0 
;               11: aload_1 
;               12: invokevirtual 42 (Interpretor/openMod (Ljava/lang/String;)V) 
;               15: goto 92 
;               18: aload_1 
;               19: ldc 52 ("VISIBLE") 
;               21: iconst_0 
;               22: invokevirtual 6 (java/lang/String/startsWith (Ljava/lang/String;I)Z) 
;               25: ifeq 11 
;               28: aload_0 
;               29: aload_1 
;               30: invokevirtual 58 (Interpretor/visible (Ljava/lang/String;)V) 
;               33: goto 74 
;               36: aload_1 
;               37: ldc 65 ("KTHXBYE") 
;               39: invokevirtual 70 (java/lang/String/equals (Ljava/lang/Object;)Z) 
;               42: ifeq 10 
;               45: aload_0 
;               46: invokevirtual 32 (Interpretor/exit ()V) 
;               49: goto 58 
;               52: aload_0 
;               53: ldc 83 ("'") 
;               55: dup 
;               56: ifnull 6 
;               59: goto 6 
;               62: pop 
;               63: ldc 60 ("null") 
;               65: aload_1 
;               66: dup 
;               67: ifnull 6 
;               70: goto 6 
;               73: pop 
;               74: ldc 60 ("null") 
;               76: invokevirtual 45 (java/lang/String/concat (Ljava/lang/String;)Ljava/lang/String;) 
;               79: dup 
;               80: ifnull 6 
;               83: goto 6 
;               86: pop 
;               87: ldc 60 ("null") 
;               89: ldc 12 ("' can not be recognized") 
;               91: dup 
;               92: ifnull 6 
;               95: goto 6 
;               98: pop 
;               99: ldc 60 ("null") 
;              101: invokevirtual 45 (java/lang/String/concat (Ljava/lang/String;)Ljava/lang/String;) 
;              104: invokevirtual 93 (Interpretor/crashed (Ljava/lang/String;)V) 
;              107: return 
;         exception_table_length 0
;         attributes_count 0


; methods[6] (offset 0x598) :
;     access_flags 0x1 [ ACC_PUBLIC ]
;     name_index 25 (visible)
;     descriptor_index 30 ((Ljava/lang/String;)V)
;     attributes_count 1
;     method_attributes[0] :
;         name_index 59 (Code)
;         attribute_length 64
;         max_stack 4
;         max_locals 3
;         code_length 52
;         code :
;                0: aload_0 
;                1: getfield 104 (Interpretor/ioImported Z) 
;                4: ifeq 7 
;                7: iconst_0 
;                8: goto 4 
;               11: iconst_1 
;               12: ifeq 9 
;               15: aload_0 
;               16: ldc 36 ("Can not execute VISIBLE with out stdio") 
;               18: invokevirtual 93 (Interpretor/crashed (Ljava/lang/String;)V) 
;               21: aload_1 
;               22: ldc 28 (9) 
;               24: aload_1 
;               25: invokevirtual 9 (java/lang/String/length ()I) 
;               28: iconst_1 
;               29: isub 
;               30: invokevirtual 71 (java/lang/String/substring (II)Ljava/lang/String;) 
;               33: dup 
;               34: astore_2 
;               35: pop 
;               36: aload_0 
;               37: getfield 57 (Interpretor/f Ljoos/lib/JoosIO;) 
;               40: aload_0 
;               41: getfield 73 (Interpretor/escape LStringEscapeUtils;) 
;               44: aload_2 
;               45: invokevirtual 97 (StringEscapeUtils/escape (Ljava/lang/String;)Ljava/lang/String;) 
;               48: invokevirtual 74 (joos/lib/JoosIO/println (Ljava/lang/String;)V) 
;               51: return 
;         exception_table_length 0
;         attributes_count 0


; methods[7] (offset 0x5e6) :
;     access_flags 0x1 [ ACC_PUBLIC ]
;     name_index 63 (openMod)
;     descriptor_index 30 ((Ljava/lang/String;)V)
;     attributes_count 1
;     method_attributes[0] :
;         name_index 59 (Code)
;         attribute_length 44
;         max_stack 3
;         max_locals 2
;         code_length 32
;         code :
;                0: aload_1 
;                1: ldc 11 ("CAN HAS STDIO?") 
;                3: invokevirtual 70 (java/lang/String/equals (Ljava/lang/Object;)Z) 
;                6: ifeq 7 
;                9: iconst_0 
;               10: goto 4 
;               13: iconst_1 
;               14: ifeq 9 
;               17: aload_0 
;               18: ldc 72 ("Only module 'STDIO' is supported") 
;               20: invokevirtual 93 (Interpretor/crashed (Ljava/lang/String;)V) 
;               23: iconst_1 
;               24: dup 
;               25: aload_0 
;               26: swap 
;               27: putfield 104 (Interpretor/ioImported Z) 
;               30: pop 
;               31: return 
;         exception_table_length 0
;         attributes_count 0



; attributes_count 1

; class_attributes[0] (offset 0x622) :
;     name_index 5 (SourceFile)
;     attribute_length 2
;     sourcefile_index 34

; End of file reached successfully. Enjoy :)
