; magic number 0xCAFEBABE
; bytecode version 45.3

; constant pool count 166
; cp[1] (offset 0xd) -> CONSTANT_String 7
; cp[2] (offset 0x12) -> CONSTANT_Methodref 81, 69
; cp[3] (offset 0x1c) -> CONSTANT_Utf8 "println"
; cp[4] (offset 0x21) -> CONSTANT_NameAndType 140, 106
; cp[5] (offset 0x26) -> CONSTANT_NameAndType 9, 95
; cp[6] (offset 0x31) -> CONSTANT_Utf8 "getSouth"
; cp[7] (offset 0x45) -> CONSTANT_Utf8 " treasure(s) and "
; cp[8] (offset 0x4a) -> CONSTANT_Methodref 62, 133
; cp[9] (offset 0x53) -> CONSTANT_Utf8 "equals"
; cp[10] (offset 0x58) -> CONSTANT_Methodref 81, 156
; cp[11] (offset 0x5b) -> CONSTANT_String 164
; cp[12] (offset 0x61) -> CONSTANT_Utf8 "()V"
; cp[13] (offset 0x64) -> CONSTANT_String 28
; cp[14] (offset 0x67) -> CONSTANT_Class 68
; cp[15] (offset 0x6a) -> CONSTANT_String 45
; cp[16] (offset 0x6f) -> CONSTANT_Methodref 91, 100
; cp[17] (offset 0x7a) -> CONSTANT_Utf8 "toString"
; cp[18] (offset 0x7f) -> CONSTANT_Methodref 62, 96
; cp[19] (offset 0x8a) -> CONSTANT_Utf8 "()LRoom;"
; cp[20] (offset 0x8d) -> CONSTANT_String 54
; cp[21] (offset 0x92) -> CONSTANT_Integer 9
; cp[22] (offset 0x97) -> CONSTANT_Utf8 "\n\n"
; cp[23] (offset 0x9c) -> CONSTANT_Integer 8
; cp[24] (offset 0xa1) -> CONSTANT_Integer 20
; cp[25] (offset 0xa6) -> CONSTANT_Integer 7
; cp[26] (offset 0xab) -> CONSTANT_Integer 6
; cp[27] (offset 0xb0) -> CONSTANT_Methodref 117, 108
; cp[28] (offset 0x107) -> CONSTANT_Utf8 "You spend the rest of your days wandering this bizarre world. Better luck next time!"
; cp[29] (offset 0x10c) -> CONSTANT_Methodref 81, 104
; cp[30] (offset 0x10f) -> CONSTANT_String 120
; cp[31] (offset 0x112) -> CONSTANT_String 148
; cp[32] (offset 0x11b) -> CONSTANT_Utf8 " died."
; cp[33] (offset 0x133) -> CONSTANT_Utf8 "(Ljava/lang/String;)V"
; cp[34] (offset 0x142) -> CONSTANT_Utf8 "You go east."
; cp[35] (offset 0x14d) -> CONSTANT_Utf8 "testLoop"
; cp[36] (offset 0x184) -> CONSTANT_Utf8 "You've escaped this bizarre world! You are now free."
; cp[37] (offset 0x19c) -> CONSTANT_Utf8 "(Ljava/lang/String;)I"
; cp[38] (offset 0x19f) -> CONSTANT_String 84
; cp[39] (offset 0x1a4) -> CONSTANT_Integer 15
; cp[40] (offset 0x1ba) -> CONSTANT_Utf8 "You have given up, "
; cp[41] (offset 0x1bf) -> CONSTANT_Integer 12
; cp[42] (offset 0x1c2) -> CONSTANT_Class 83
; cp[43] (offset 0x1c7) -> CONSTANT_NameAndType 88, 92
; cp[44] (offset 0x1cc) -> CONSTANT_Integer 11
; cp[45] (offset 0x1d3) -> CONSTANT_Utf8 "null"
; cp[46] (offset 0x1d6) -> CONSTANT_String 58
; cp[47] (offset 0x1db) -> CONSTANT_Integer 10
; cp[48] (offset 0x1e0) -> CONSTANT_Utf8 ".\n"
; cp[49] (offset 0x1ea) -> CONSTANT_Utf8 "give up"
; cp[50] (offset 0x1f8) -> CONSTANT_Utf8 "randomRange"
; cp[51] (offset 0x1fd) -> CONSTANT_NameAndType 122, 126
; cp[52] (offset 0x209) -> CONSTANT_Utf8 "enterRoom"
; cp[53] (offset 0x214) -> CONSTANT_Utf8 "GrueHunt"
; cp[54] (offset 0x2da) -> CONSTANT_Utf8 "╔═╝┏━┓╻ ╻┏━╸ ║ ║╻ ╻┏┓╻╺┳╸\n║ ║┣┳┛┃ ┃┣╸  ╔═║┃ ┃┃┗┫ ┃ \n══╝╹┗╸┗━┛┗━╸ ╝ ╝┗━┛╹ ╹ ╹ "
; cp[55] (offset 0x2dd) -> CONSTANT_String 158
; cp[56] (offset 0x2f6) -> CONSTANT_Utf8 "(Ljava/lang/String;I)I"
; cp[57] (offset 0x2fb) -> CONSTANT_Methodref 63, 100
; cp[58] (offset 0x32f) -> CONSTANT_Utf8 "Welcome to GrueHunt! Please don't feed the grues."
; cp[59] (offset 0x332) -> CONSTANT_String 34
; cp[60] (offset 0x335) -> CONSTANT_String 40
; cp[61] (offset 0x33a) -> CONSTANT_Methodref 117, 102
; cp[62] (offset 0x33d) -> CONSTANT_Class 157
; cp[63] (offset 0x340) -> CONSTANT_Class 109
; cp[64] (offset 0x350) -> CONSTANT_Utf8 "performAction"
; cp[65] (offset 0x358) -> CONSTANT_Utf8 "north"
; cp[66] (offset 0x364) -> CONSTANT_Utf8 "You have "
; cp[67] (offset 0x369) -> CONSTANT_Methodref 62, 74
; cp[68] (offset 0x37c) -> CONSTANT_Utf8 "java/lang/String"
; cp[69] (offset 0x381) -> CONSTANT_NameAndType 50, 160
; cp[70] (offset 0x39e) -> CONSTANT_Utf8 "There is no exit that way."
; cp[71] (offset 0x3a6) -> CONSTANT_Utf8 "south"
; cp[72] (offset 0x3a9) -> CONSTANT_String 93
; cp[73] (offset 0x3ac) -> CONSTANT_String 70
; cp[74] (offset 0x3b1) -> CONSTANT_NameAndType 82, 33
; cp[75] (offset 0x3b4) -> CONSTANT_String 65
; cp[76] (offset 0x3c9) -> CONSTANT_Utf8 "What is your name?"
; cp[77] (offset 0x3ce) -> CONSTANT_Methodref 81, 115
; cp[78] (offset 0x3db) -> CONSTANT_Utf8 "GrueHunt.j"
; cp[79] (offset 0x3e7) -> CONSTANT_Utf8 " coin(s)."
; cp[80] (offset 0x3ee) -> CONSTANT_Utf8 "main"
; cp[81] (offset 0x3f1) -> CONSTANT_Class 159
; cp[82] (offset 0x3f9) -> CONSTANT_Utf8 "print"
; cp[83] (offset 0x406) -> CONSTANT_Utf8 "RoomAction"
; cp[84] (offset 0x41f) -> CONSTANT_Utf8 "Thank you for playing\n"
; cp[85] (offset 0x424) -> CONSTANT_NameAndType 35, 90
; cp[86] (offset 0x429) -> CONSTANT_Methodref 14, 5
; cp[87] (offset 0x42e) -> CONSTANT_Methodref 42, 154
; cp[88] (offset 0x437) -> CONSTANT_Utf8 "concat"
; cp[89] (offset 0x43a) -> CONSTANT_String 71
; cp[90] (offset 0x463) -> CONSTANT_Utf8 "(Ljoos/lib/JoosIO;Z)Ljava/lang/String;"
; cp[91] (offset 0x466) -> CONSTANT_Class 53
; cp[92] (offset 0x48f) -> CONSTANT_Utf8 "(Ljava/lang/String;)Ljava/lang/String;"
; cp[93] (offset 0x496) -> CONSTANT_Utf8 "Dave"
; cp[94] (offset 0x49b) -> CONSTANT_Methodref 81, 4
; cp[95] (offset 0x4b3) -> CONSTANT_Utf8 "(Ljava/lang/Object;)Z"
; cp[96] (offset 0x4b8) -> CONSTANT_NameAndType 113, 99
; cp[97] (offset 0x4bd) -> CONSTANT_Integer 100
; cp[98] (offset 0x4c2) -> CONSTANT_Methodref 62, 100
; cp[99] (offset 0x4d9) -> CONSTANT_Utf8 "()Ljava/lang/String;"
; cp[100] (offset 0x4de) -> CONSTANT_NameAndType 122, 12
; cp[101] (offset 0x4e1) -> CONSTANT_String 143
; cp[102] (offset 0x4e6) -> CONSTANT_NameAndType 122, 155
; cp[103] (offset 0x4e9) -> CONSTANT_String 129
; cp[104] (offset 0x4ee) -> CONSTANT_NameAndType 161, 19
; cp[105] (offset 0x4f1) -> CONSTANT_String 32
; cp[106] (offset 0x502) -> CONSTANT_Utf8 "()LRoomAction;"
; cp[107] (offset 0x509) -> CONSTANT_Utf8 "Code"
; cp[108] (offset 0x50e) -> CONSTANT_NameAndType 17, 99
; cp[109] (offset 0x521) -> CONSTANT_Utf8 "java/lang/Object"
; cp[110] (offset 0x524) -> CONSTANT_String 22
; cp[111] (offset 0x527) -> CONSTANT_String 49
; cp[112] (offset 0x52a) -> CONSTANT_String 76
; cp[113] (offset 0x535) -> CONSTANT_Utf8 "readLine"
; cp[114] (offset 0x538) -> CONSTANT_String 36
; cp[115] (offset 0x53d) -> CONSTANT_NameAndType 52, 12
; cp[116] (offset 0x54d) -> CONSTANT_Utf8 "You go south."
; cp[117] (offset 0x550) -> CONSTANT_Class 151
; cp[118] (offset 0x555) -> CONSTANT_Methodref 81, 51
; cp[119] (offset 0x56e) -> CONSTANT_Utf8 "([Ljava/lang/String;)V"
; cp[120] (offset 0x5a5) -> CONSTANT_Utf8 "You suddenly notice the new place you find yourself."
; cp[121] (offset 0x5aa) -> CONSTANT_NameAndType 153, 56
; cp[122] (offset 0x5b3) -> CONSTANT_Utf8 "<init>"
; cp[123] (offset 0x5bb) -> CONSTANT_Utf8 " has "
; cp[124] (offset 0x5be) -> CONSTANT_String 48
; cp[125] (offset 0x5c1) -> CONSTANT_String 66
; cp[126] (offset 0x5e0) -> CONSTANT_Utf8 "(LRoom;Ljava/lang/String;I)V"
; cp[127] (offset 0x5e3) -> CONSTANT_String 165
; cp[128] (offset 0x5f3) -> CONSTANT_Utf8 " treasure(s)."
; cp[129] (offset 0x5fa) -> CONSTANT_Utf8 "west"
; cp[130] (offset 0x5fd) -> CONSTANT_String 149
; cp[131] (offset 0x60a) -> CONSTANT_Utf8 "SourceFile"
; cp[132] (offset 0x61a) -> CONSTANT_Utf8 "You go north."
; cp[133] (offset 0x61f) -> CONSTANT_NameAndType 3, 33
; cp[134] (offset 0x622) -> CONSTANT_String 116
; cp[135] (offset 0x627) -> CONSTANT_NameAndType 162, 19
; cp[136] (offset 0x62c) -> CONSTANT_NameAndType 145, 19
; cp[137] (offset 0x631) -> CONSTANT_Methodref 81, 135
; cp[138] (offset 0x636) -> CONSTANT_Methodref 14, 121
; cp[139] (offset 0x639) -> CONSTANT_String 123
; cp[140] (offset 0x649) -> CONSTANT_Utf8 "getRoomAction"
; cp[141] (offset 0x64c) -> CONSTANT_String 128
; cp[142] (offset 0x64f) -> CONSTANT_String 79
; cp[143] (offset 0x668) -> CONSTANT_Utf8 " hit points remaining."
; cp[144] (offset 0x66b) -> CONSTANT_String 132
; cp[145] (offset 0x675) -> CONSTANT_Utf8 "getWest"
; cp[146] (offset 0x67a) -> CONSTANT_Methodref 81, 136
; cp[147] (offset 0x67f) -> CONSTANT_Methodref 91, 85
; cp[148] (offset 0x683) -> CONSTANT_Utf8 "."
; cp[149] (offset 0x68a) -> CONSTANT_Utf8 "east"
; cp[150] (offset 0x68f) -> CONSTANT_Methodref 14, 43
; cp[151] (offset 0x6a3) -> CONSTANT_Utf8 "java/lang/Integer"
; cp[152] (offset 0x6a6) -> CONSTANT_String 163
; cp[153] (offset 0x6b0) -> CONSTANT_Utf8 "indexOf"
; cp[154] (offset 0x6b5) -> CONSTANT_NameAndType 64, 37
; cp[155] (offset 0x6bc) -> CONSTANT_Utf8 "(I)V"
; cp[156] (offset 0x6c1) -> CONSTANT_NameAndType 6, 19
; cp[157] (offset 0x6d3) -> CONSTANT_Utf8 "joos/lib/JoosIO"
; cp[158] (offset 0x6d7) -> CONSTANT_Utf8 "\n"
; cp[159] (offset 0x6de) -> CONSTANT_Utf8 "Room"
; cp[160] (offset 0x6e5) -> CONSTANT_Utf8 "(I)I"
; cp[161] (offset 0x6f0) -> CONSTANT_Utf8 "getNorth"
; cp[162] (offset 0x6fa) -> CONSTANT_Utf8 "getEast"
; cp[163] (offset 0x70e) -> CONSTANT_Utf8 " has accumulated "
; cp[164] (offset 0x71d) -> CONSTANT_Utf8 "You go west."
; cp[165] (offset 0x720) -> CONSTANT_Utf8 ""

; access flags = 0x21 [ ACC_SUPER ACC_PUBLIC ]
; this_class index = 91
; super_class index = 63

; interfaces_count = 0


; fields_count = 0

; methods_count 3

; methods[0] (offset 0x72c) :
;     access_flags 0x1 [ ACC_PUBLIC ]
;     name_index 122 (<init>)
;     descriptor_index 12 (()V)
;     attributes_count 1
;     method_attributes[0] :
;         name_index 107 (Code)
;         attribute_length 17
;         max_stack 1
;         max_locals 1
;         code_length 5
;         code :
;                0: aload_0 
;                1: invokespecial 57 (java/lang/Object/<init> ()V) 
;                4: return 
;         exception_table_length 0
;         attributes_count 0


; methods[1] (offset 0x74b) :
;     access_flags 0x1 [ ACC_PUBLIC ]
;     name_index 35 (testLoop)
;     descriptor_index 90 ((Ljoos/lib/JoosIO;Z)Ljava/lang/String;)
;     attributes_count 1
;     method_attributes[0] :
;         name_index 107 (Code)
;         attribute_length 38
;         max_stack 2
;         max_locals 4
;         code_length 26
;         code :
;                0: aconst_null 
;                1: dup 
;                2: astore_3 
;                3: pop 
;                4: iload_2 
;                5: ifeq 7 
;                8: iconst_0 
;                9: goto 4 
;               12: iconst_1 
;               13: ifeq 10 
;               16: aload_1 
;               17: invokevirtual 18 (joos/lib/JoosIO/readLine ()Ljava/lang/String;) 
;               20: dup 
;               21: astore_3 
;               22: pop 
;               23: aload_3 
;               24: areturn 
;               25: nop 
;         exception_table_length 0
;         attributes_count 0


; methods[2] (offset 0x77f) :
;     access_flags 0x9 [ ACC_STATIC ACC_PUBLIC ]
;     name_index 80 (main)
;     descriptor_index 119 (([Ljava/lang/String;)V)
;     attributes_count 1
;     method_attributes[0] :
;         name_index 107 (Code)
;         attribute_length 1643
;         max_stack 5
;         max_locals 16
;         code_length 1631
;         code :
;                0: new 91 (GrueHunt) 
;                3: dup 
;                4: invokespecial 16 (GrueHunt/<init> ()V) 
;                7: dup 
;                8: astore 14 
;               10: pop 
;               11: iconst_0 
;               12: dup 
;               13: istore 8 
;               15: pop 
;               16: ldc 20 ("╔═╝┏━┓╻ ╻┏━╸ ║ ║╻ ╻┏┓╻╺┳╸\n║ ║┣┳┛┃ ┃┣╸  ╔═║┃ ┃┃┗┫ ┃ \n══╝╹┗╸┗━┛┗━╸ ╝ ╝┗━┛╹ ╹ ╹ ") 
;               18: dup 
;               19: astore 11 
;               21: pop 
;               22: ldc 24 (20) 
;               24: dup 
;               25: istore 13 
;               27: pop 
;               28: ldc 97 (100) 
;               30: dup 
;               31: istore 7 
;               33: pop 
;               34: new 62 (joos/lib/JoosIO) 
;               37: dup 
;               38: invokespecial 98 (joos/lib/JoosIO/<init> ()V) 
;               41: dup 
;               42: astore_1 
;               43: pop 
;               44: ldc 44 (11) 
;               46: dup 
;               47: istore 6 
;               49: pop 
;               50: new 81 (Room) 
;               53: dup 
;               54: aconst_null 
;               55: ldc 15 ("null") 
;               57: iload 6 
;               59: invokespecial 118 (Room/<init> (LRoom;Ljava/lang/String;I)V) 
;               62: dup 
;               63: astore 12 
;               65: pop 
;               66: iconst_0 
;               67: dup 
;               68: istore_2 
;               69: pop 
;               70: iconst_0 
;               71: dup 
;               72: istore_3 
;               73: pop 
;               74: ldc 47 (10) 
;               76: dup 
;               77: istore 4 
;               79: pop 
;               80: aload_1 
;               81: ldc 55 ("\n") 
;               83: dup 
;               84: ifnull 6 
;               87: goto 6 
;               90: pop 
;               91: ldc 15 ("null") 
;               93: aload 11 
;               95: dup 
;               96: ifnull 6 
;               99: goto 6 
;              102: pop 
;              103: ldc 15 ("null") 
;              105: invokevirtual 150 (java/lang/String/concat (Ljava/lang/String;)Ljava/lang/String;) 
;              108: invokevirtual 8 (joos/lib/JoosIO/println (Ljava/lang/String;)V) 
;              111: aload_1 
;              112: ldc 55 ("\n") 
;              114: invokevirtual 8 (joos/lib/JoosIO/println (Ljava/lang/String;)V) 
;              117: aload_1 
;              118: ldc 46 ("Welcome to GrueHunt! Please don't feed the grues.") 
;              120: invokevirtual 8 (joos/lib/JoosIO/println (Ljava/lang/String;)V) 
;              123: aload_1 
;              124: ldc 112 ("What is your name?") 
;              126: invokevirtual 8 (joos/lib/JoosIO/println (Ljava/lang/String;)V) 
;              129: aload_1 
;              130: invokevirtual 18 (joos/lib/JoosIO/readLine ()Ljava/lang/String;) 
;              133: dup 
;              134: astore 9 
;              136: pop 
;              137: aload 9 
;              139: aconst_null 
;              140: if_acmpeq 7 
;              143: iconst_0 
;              144: goto 4 
;              147: iconst_1 
;              148: dup 
;              149: ifne 11 
;              152: pop 
;              153: aload 9 
;              155: ldc 127 ("") 
;              157: invokevirtual 86 (java/lang/String/equals (Ljava/lang/Object;)Z) 
;              160: ifeq 9 
;              163: ldc 72 ("Dave") 
;              165: dup 
;              166: astore 9 
;              168: pop 
;              169: aload 12 
;              171: invokevirtual 77 (Room/enterRoom ()V) 
;              174: aload 14 
;              176: aload_1 
;              177: iload 8 
;              179: invokevirtual 147 (GrueHunt/testLoop (Ljoos/lib/JoosIO;Z)Ljava/lang/String;) 
;              182: dup 
;              183: astore 10 
;              185: aconst_null 
;              186: if_acmpne 7 
;              189: iconst_0 
;              190: goto 4 
;              193: iconst_1 
;              194: ifeq 1195 
;              197: aload_1 
;              198: ldc 127 ("") 
;              200: invokevirtual 8 (joos/lib/JoosIO/println (Ljava/lang/String;)V) 
;              203: aload 10 
;              205: ldc 111 ("give up") 
;              207: iconst_0 
;              208: invokevirtual 138 (java/lang/String/indexOf (Ljava/lang/String;I)I) 
;              211: iconst_0 
;              212: if_icmpge 7 
;              215: iconst_0 
;              216: goto 4 
;              219: iconst_1 
;              220: ifeq 73 
;              223: aload_1 
;              224: ldc 60 ("You have given up, ") 
;              226: dup 
;              227: ifnull 6 
;              230: goto 6 
;              233: pop 
;              234: ldc 15 ("null") 
;              236: aload 9 
;              238: dup 
;              239: ifnull 6 
;              242: goto 6 
;              245: pop 
;              246: ldc 15 ("null") 
;              248: invokevirtual 150 (java/lang/String/concat (Ljava/lang/String;)Ljava/lang/String;) 
;              251: dup 
;              252: ifnull 6 
;              255: goto 6 
;              258: pop 
;              259: ldc 15 ("null") 
;              261: ldc 31 (".") 
;              263: dup 
;              264: ifnull 6 
;              267: goto 6 
;              270: pop 
;              271: ldc 15 ("null") 
;              273: invokevirtual 150 (java/lang/String/concat (Ljava/lang/String;)Ljava/lang/String;) 
;              276: invokevirtual 8 (joos/lib/JoosIO/println (Ljava/lang/String;)V) 
;              279: aload_1 
;              280: ldc 13 ("You spend the rest of your days wandering this bizarre world. Better luck next time!") 
;              282: invokevirtual 8 (joos/lib/JoosIO/println (Ljava/lang/String;)V) 
;              285: iconst_1 
;              286: dup 
;              287: istore 8 
;              289: pop 
;              290: goto 1072 
;              293: aload 10 
;              295: ldc 75 ("north") 
;              297: iconst_0 
;              298: invokevirtual 138 (java/lang/String/indexOf (Ljava/lang/String;I)I) 
;              301: iconst_0 
;              302: if_icmpge 7 
;              305: iconst_0 
;              306: goto 4 
;              309: iconst_1 
;              310: ifeq 50 
;              313: aload 12 
;              315: invokevirtual 29 (Room/getNorth ()LRoom;) 
;              318: dup 
;              319: astore 15 
;              321: pop 
;              322: aload 15 
;              324: aconst_null 
;              325: if_acmpeq 7 
;              328: iconst_0 
;              329: goto 4 
;              332: iconst_1 
;              333: ifeq 12 
;              336: aload_1 
;              337: ldc 73 ("There is no exit that way.") 
;              339: invokevirtual 8 (joos/lib/JoosIO/println (Ljava/lang/String;)V) 
;              342: goto 15 
;              345: aload 15 
;              347: dup 
;              348: astore 12 
;              350: pop 
;              351: aload_1 
;              352: ldc 144 ("You go north.") 
;              354: invokevirtual 8 (joos/lib/JoosIO/println (Ljava/lang/String;)V) 
;              357: goto 1005 
;              360: aload 10 
;              362: ldc 89 ("south") 
;              364: iconst_0 
;              365: invokevirtual 138 (java/lang/String/indexOf (Ljava/lang/String;I)I) 
;              368: iconst_0 
;              369: if_icmpge 7 
;              372: iconst_0 
;              373: goto 4 
;              376: iconst_1 
;              377: ifeq 50 
;              380: aload 12 
;              382: invokevirtual 10 (Room/getSouth ()LRoom;) 
;              385: dup 
;              386: astore 15 
;              388: pop 
;              389: aload 15 
;              391: aconst_null 
;              392: if_acmpeq 7 
;              395: iconst_0 
;              396: goto 4 
;              399: iconst_1 
;              400: ifeq 12 
;              403: aload_1 
;              404: ldc 73 ("There is no exit that way.") 
;              406: invokevirtual 8 (joos/lib/JoosIO/println (Ljava/lang/String;)V) 
;              409: goto 15 
;              412: aload 15 
;              414: dup 
;              415: astore 12 
;              417: pop 
;              418: aload_1 
;              419: ldc 134 ("You go south.") 
;              421: invokevirtual 8 (joos/lib/JoosIO/println (Ljava/lang/String;)V) 
;              424: goto 938 
;              427: aload 10 
;              429: ldc 103 ("west") 
;              431: iconst_0 
;              432: invokevirtual 138 (java/lang/String/indexOf (Ljava/lang/String;I)I) 
;              435: iconst_0 
;              436: if_icmpge 7 
;              439: iconst_0 
;              440: goto 4 
;              443: iconst_1 
;              444: ifeq 50 
;              447: aload 12 
;              449: invokevirtual 146 (Room/getWest ()LRoom;) 
;              452: dup 
;              453: astore 15 
;              455: pop 
;              456: aload 15 
;              458: aconst_null 
;              459: if_acmpeq 7 
;              462: iconst_0 
;              463: goto 4 
;              466: iconst_1 
;              467: ifeq 12 
;              470: aload_1 
;              471: ldc 73 ("There is no exit that way.") 
;              473: invokevirtual 8 (joos/lib/JoosIO/println (Ljava/lang/String;)V) 
;              476: goto 15 
;              479: aload 15 
;              481: dup 
;              482: astore 12 
;              484: pop 
;              485: aload_1 
;              486: ldc 11 ("You go west.") 
;              488: invokevirtual 8 (joos/lib/JoosIO/println (Ljava/lang/String;)V) 
;              491: goto 871 
;              494: aload 10 
;              496: ldc 130 ("east") 
;              498: iconst_0 
;              499: invokevirtual 138 (java/lang/String/indexOf (Ljava/lang/String;I)I) 
;              502: iconst_0 
;              503: if_icmpge 7 
;              506: iconst_0 
;              507: goto 4 
;              510: iconst_1 
;              511: ifeq 50 
;              514: aload 12 
;              516: invokevirtual 137 (Room/getEast ()LRoom;) 
;              519: dup 
;              520: astore 15 
;              522: pop 
;              523: aload 15 
;              525: aconst_null 
;              526: if_acmpeq 7 
;              529: iconst_0 
;              530: goto 4 
;              533: iconst_1 
;              534: ifeq 12 
;              537: aload_1 
;              538: ldc 73 ("There is no exit that way.") 
;              540: invokevirtual 8 (joos/lib/JoosIO/println (Ljava/lang/String;)V) 
;              543: goto 15 
;              546: aload 15 
;              548: dup 
;              549: astore 12 
;              551: pop 
;              552: aload_1 
;              553: ldc 59 ("You go east.") 
;              555: invokevirtual 8 (joos/lib/JoosIO/println (Ljava/lang/String;)V) 
;              558: goto 804 
;              561: aload 12 
;              563: invokevirtual 94 (Room/getRoomAction ()LRoomAction;) 
;              566: aload 10 
;              568: invokevirtual 87 (RoomAction/performAction (Ljava/lang/String;)I) 
;              571: dup 
;              572: istore 5 
;              574: pop 
;              575: iload 5 
;              577: iconst_0 
;              578: if_icmpeq 7 
;              581: iconst_0 
;              582: goto 4 
;              585: iconst_1 
;              586: ifeq 6 
;              589: goto 652 
;              592: iload 5 
;              594: iconst_1 
;              595: if_icmpeq 7 
;              598: iconst_0 
;              599: goto 4 
;              602: iconst_1 
;              603: ifeq 11 
;              606: iconst_0 
;              607: dup 
;              608: istore 4 
;              610: pop 
;              611: goto 630 
;              614: iload 5 
;              616: iconst_2 
;              617: if_icmpeq 7 
;              620: iconst_0 
;              621: goto 4 
;              624: iconst_1 
;              625: ifeq 37 
;              628: aload_1 
;              629: aload 9 
;              631: dup 
;              632: ifnull 6 
;              635: goto 6 
;              638: pop 
;              639: ldc 15 ("null") 
;              641: ldc 124 (".\n") 
;              643: dup 
;              644: ifnull 6 
;              647: goto 6 
;              650: pop 
;              651: ldc 15 ("null") 
;              653: invokevirtual 150 (java/lang/String/concat (Ljava/lang/String;)Ljava/lang/String;) 
;              656: invokevirtual 67 (joos/lib/JoosIO/print (Ljava/lang/String;)V) 
;              659: goto 582 
;              662: iload 5 
;              664: iconst_3 
;              665: if_icmpeq 7 
;              668: iconst_0 
;              669: goto 4 
;              672: iconst_1 
;              673: ifeq 67 
;              676: iload_3 
;              677: iconst_1 
;              678: iadd 
;              679: dup 
;              680: istore_3 
;              681: pop 
;              682: aload_1 
;              683: ldc 125 ("You have ") 
;              685: dup 
;              686: ifnull 6 
;              689: goto 6 
;              692: pop 
;              693: ldc 15 ("null") 
;              695: new 117 (java/lang/Integer) 
;              698: dup 
;              699: iload_3 
;              700: invokespecial 61 (java/lang/Integer/<init> (I)V) 
;              703: invokevirtual 27 (java/lang/Integer/toString ()Ljava/lang/String;) 
;              706: invokevirtual 150 (java/lang/String/concat (Ljava/lang/String;)Ljava/lang/String;) 
;              709: dup 
;              710: ifnull 6 
;              713: goto 6 
;              716: pop 
;              717: ldc 15 ("null") 
;              719: ldc 141 (" treasure(s).") 
;              721: dup 
;              722: ifnull 6 
;              725: goto 6 
;              728: pop 
;              729: ldc 15 ("null") 
;              731: invokevirtual 150 (java/lang/String/concat (Ljava/lang/String;)Ljava/lang/String;) 
;              734: invokevirtual 8 (joos/lib/JoosIO/println (Ljava/lang/String;)V) 
;              737: goto 504 
;              740: iload 5 
;              742: iconst_4 
;              743: if_icmpeq 7 
;              746: iconst_0 
;              747: goto 4 
;              750: iconst_1 
;              751: ifeq 61 
;              754: aload_1 
;              755: ldc 125 ("You have ") 
;              757: dup 
;              758: ifnull 6 
;              761: goto 6 
;              764: pop 
;              765: ldc 15 ("null") 
;              767: new 117 (java/lang/Integer) 
;              770: dup 
;              771: iload_3 
;              772: invokespecial 61 (java/lang/Integer/<init> (I)V) 
;              775: invokevirtual 27 (java/lang/Integer/toString ()Ljava/lang/String;) 
;              778: invokevirtual 150 (java/lang/String/concat (Ljava/lang/String;)Ljava/lang/String;) 
;              781: dup 
;              782: ifnull 6 
;              785: goto 6 
;              788: pop 
;              789: ldc 15 ("null") 
;              791: ldc 141 (" treasure(s).") 
;              793: dup 
;              794: ifnull 6 
;              797: goto 6 
;              800: pop 
;              801: ldc 15 ("null") 
;              803: invokevirtual 150 (java/lang/String/concat (Ljava/lang/String;)Ljava/lang/String;) 
;              806: invokevirtual 8 (joos/lib/JoosIO/println (Ljava/lang/String;)V) 
;              809: goto 432 
;              812: iload 5 
;              814: iconst_5 
;              815: if_icmpeq 7 
;              818: iconst_0 
;              819: goto 4 
;              822: iconst_1 
;              823: ifeq 67 
;              826: iload_2 
;              827: iconst_1 
;              828: iadd 
;              829: dup 
;              830: istore_2 
;              831: pop 
;              832: aload_1 
;              833: ldc 125 ("You have ") 
;              835: dup 
;              836: ifnull 6 
;              839: goto 6 
;              842: pop 
;              843: ldc 15 ("null") 
;              845: new 117 (java/lang/Integer) 
;              848: dup 
;              849: iload_2 
;              850: invokespecial 61 (java/lang/Integer/<init> (I)V) 
;              853: invokevirtual 27 (java/lang/Integer/toString ()Ljava/lang/String;) 
;              856: invokevirtual 150 (java/lang/String/concat (Ljava/lang/String;)Ljava/lang/String;) 
;              859: dup 
;              860: ifnull 6 
;              863: goto 6 
;              866: pop 
;              867: ldc 15 ("null") 
;              869: ldc 142 (" coin(s).") 
;              871: dup 
;              872: ifnull 6 
;              875: goto 6 
;              878: pop 
;              879: ldc 15 ("null") 
;              881: invokevirtual 150 (java/lang/String/concat (Ljava/lang/String;)Ljava/lang/String;) 
;              884: invokevirtual 8 (joos/lib/JoosIO/println (Ljava/lang/String;)V) 
;              887: goto 354 
;              890: iload 5 
;              892: ldc 26 (6) 
;              894: if_icmpeq 7 
;              897: iconst_0 
;              898: goto 4 
;              901: iconst_1 
;              902: ifeq 61 
;              905: aload_1 
;              906: ldc 125 ("You have ") 
;              908: dup 
;              909: ifnull 6 
;              912: goto 6 
;              915: pop 
;              916: ldc 15 ("null") 
;              918: new 117 (java/lang/Integer) 
;              921: dup 
;              922: iload_2 
;              923: invokespecial 61 (java/lang/Integer/<init> (I)V) 
;              926: invokevirtual 27 (java/lang/Integer/toString ()Ljava/lang/String;) 
;              929: invokevirtual 150 (java/lang/String/concat (Ljava/lang/String;)Ljava/lang/String;) 
;              932: dup 
;              933: ifnull 6 
;              936: goto 6 
;              939: pop 
;              940: ldc 15 ("null") 
;              942: ldc 142 (" coin(s).") 
;              944: dup 
;              945: ifnull 6 
;              948: goto 6 
;              951: pop 
;              952: ldc 15 ("null") 
;              954: invokevirtual 150 (java/lang/String/concat (Ljava/lang/String;)Ljava/lang/String;) 
;              957: invokevirtual 8 (joos/lib/JoosIO/println (Ljava/lang/String;)V) 
;              960: goto 281 
;              963: iload 5 
;              965: ldc 25 (7) 
;              967: if_icmpeq 7 
;              970: iconst_0 
;              971: goto 4 
;              974: iconst_1 
;              975: ifeq 14 
;              978: iload 4 
;              980: iconst_1 
;              981: iadd 
;              982: dup 
;              983: istore 4 
;              985: pop 
;              986: goto 255 
;              989: iload 5 
;              991: ldc 23 (8) 
;              993: if_icmpeq 7 
;              996: iconst_0 
;              997: goto 4 
;             1000: iconst_1 
;             1001: ifeq 14 
;             1004: iload 4 
;             1006: iconst_2 
;             1007: iadd 
;             1008: dup 
;             1009: istore 4 
;             1011: pop 
;             1012: goto 229 
;             1015: iload 5 
;             1017: ldc 21 (9) 
;             1019: if_icmpeq 7 
;             1022: iconst_0 
;             1023: goto 4 
;             1026: iconst_1 
;             1027: ifeq 14 
;             1030: iload 4 
;             1032: iconst_1 
;             1033: isub 
;             1034: dup 
;             1035: istore 4 
;             1037: pop 
;             1038: goto 203 
;             1041: iload 5 
;             1043: ldc 47 (10) 
;             1045: if_icmpeq 7 
;             1048: iconst_0 
;             1049: goto 4 
;             1052: iconst_1 
;             1053: ifeq 14 
;             1056: iload 4 
;             1058: iconst_2 
;             1059: isub 
;             1060: dup 
;             1061: istore 4 
;             1063: pop 
;             1064: goto 177 
;             1067: iload 5 
;             1069: ldc 44 (11) 
;             1071: if_icmpeq 7 
;             1074: iconst_0 
;             1075: goto 4 
;             1078: iconst_1 
;             1079: ifeq 62 
;             1082: aload_1 
;             1083: ldc 125 ("You have ") 
;             1085: dup 
;             1086: ifnull 6 
;             1089: goto 6 
;             1092: pop 
;             1093: ldc 15 ("null") 
;             1095: new 117 (java/lang/Integer) 
;             1098: dup 
;             1099: iload 4 
;             1101: invokespecial 61 (java/lang/Integer/<init> (I)V) 
;             1104: invokevirtual 27 (java/lang/Integer/toString ()Ljava/lang/String;) 
;             1107: invokevirtual 150 (java/lang/String/concat (Ljava/lang/String;)Ljava/lang/String;) 
;             1110: dup 
;             1111: ifnull 6 
;             1114: goto 6 
;             1117: pop 
;             1118: ldc 15 ("null") 
;             1120: ldc 101 (" hit points remaining.") 
;             1122: dup 
;             1123: ifnull 6 
;             1126: goto 6 
;             1129: pop 
;             1130: ldc 15 ("null") 
;             1132: invokevirtual 150 (java/lang/String/concat (Ljava/lang/String;)Ljava/lang/String;) 
;             1135: invokevirtual 8 (joos/lib/JoosIO/println (Ljava/lang/String;)V) 
;             1138: goto 103 
;             1141: iload 5 
;             1143: ldc 41 (12) 
;             1145: if_icmpeq 7 
;             1148: iconst_0 
;             1149: goto 4 
;             1152: iconst_1 
;             1153: ifeq 88 
;             1156: aload 12 
;             1158: ldc 97 (100) 
;             1160: invokevirtual 2 (Room/randomRange (I)I) 
;             1163: dup 
;             1164: istore 7 
;             1166: pop 
;             1167: iload 7 
;             1169: iload 13 
;             1171: if_icmplt 7 
;             1174: iconst_0 
;             1175: goto 4 
;             1178: iconst_1 
;             1179: ifeq 12 
;             1182: aload_1 
;             1183: ldc 114 ("You've escaped this bizarre world! You are now free.") 
;             1185: invokevirtual 8 (joos/lib/JoosIO/println (Ljava/lang/String;)V) 
;             1188: goto 53 
;             1191: iload 6 
;             1193: iconst_1 
;             1194: isub 
;             1195: dup 
;             1196: istore 6 
;             1198: pop 
;             1199: iload 6 
;             1201: iconst_5 
;             1202: if_icmpeq 7 
;             1205: iconst_0 
;             1206: goto 4 
;             1209: iconst_1 
;             1210: ifeq 9 
;             1213: ldc 44 (11) 
;             1215: dup 
;             1216: istore 6 
;             1218: pop 
;             1219: new 81 (Room) 
;             1222: dup 
;             1223: aconst_null 
;             1224: ldc 15 ("null") 
;             1226: iload 6 
;             1228: invokespecial 118 (Room/<init> (LRoom;Ljava/lang/String;I)V) 
;             1231: dup 
;             1232: astore 12 
;             1234: pop 
;             1235: aload_1 
;             1236: ldc 30 ("You suddenly notice the new place you find yourself.") 
;             1238: invokevirtual 8 (joos/lib/JoosIO/println (Ljava/lang/String;)V) 
;             1241: iload 4 
;             1243: ldc 39 (15) 
;             1245: if_icmpgt 7 
;             1248: iconst_0 
;             1249: goto 4 
;             1252: iconst_1 
;             1253: ifeq 9 
;             1256: ldc 39 (15) 
;             1258: dup 
;             1259: istore 4 
;             1261: pop 
;             1262: iload 4 
;             1264: iconst_1 
;             1265: if_icmplt 7 
;             1268: iconst_0 
;             1269: goto 4 
;             1272: iconst_1 
;             1273: ifeq 69 
;             1276: aload_1 
;             1277: ldc 110 ("\n\n") 
;             1279: dup 
;             1280: ifnull 6 
;             1283: goto 6 
;             1286: pop 
;             1287: ldc 15 ("null") 
;             1289: aload 9 
;             1291: dup 
;             1292: ifnull 6 
;             1295: goto 6 
;             1298: pop 
;             1299: ldc 15 ("null") 
;             1301: invokevirtual 150 (java/lang/String/concat (Ljava/lang/String;)Ljava/lang/String;) 
;             1304: dup 
;             1305: ifnull 6 
;             1308: goto 6 
;             1311: pop 
;             1312: ldc 15 ("null") 
;             1314: ldc 105 (" died.") 
;             1316: dup 
;             1317: ifnull 6 
;             1320: goto 6 
;             1323: pop 
;             1324: ldc 15 ("null") 
;             1326: invokevirtual 150 (java/lang/String/concat (Ljava/lang/String;)Ljava/lang/String;) 
;             1329: invokevirtual 8 (joos/lib/JoosIO/println (Ljava/lang/String;)V) 
;             1332: iconst_0 
;             1333: dup 
;             1334: istore 4 
;             1336: pop 
;             1337: iconst_1 
;             1338: dup 
;             1339: istore 8 
;             1341: pop 
;             1342: iload 7 
;             1344: iload 13 
;             1346: if_icmplt 7 
;             1349: iconst_0 
;             1350: goto 4 
;             1353: iconst_1 
;             1354: ifeq 8 
;             1357: iconst_1 
;             1358: dup 
;             1359: istore 8 
;             1361: pop 
;             1362: iload 8 
;             1364: ifeq 7 
;             1367: iconst_0 
;             1368: goto 4 
;             1371: iconst_1 
;             1372: ifeq 14 
;             1375: aload_1 
;             1376: ldc 127 ("") 
;             1378: invokevirtual 8 (joos/lib/JoosIO/println (Ljava/lang/String;)V) 
;             1381: aload 12 
;             1383: invokevirtual 77 (Room/enterRoom ()V) 
;             1386: goto -1212 
;             1389: aload_1 
;             1390: aload 9 
;             1392: dup 
;             1393: ifnull 6 
;             1396: goto 6 
;             1399: pop 
;             1400: ldc 15 ("null") 
;             1402: ldc 152 (" has accumulated ") 
;             1404: dup 
;             1405: ifnull 6 
;             1408: goto 6 
;             1411: pop 
;             1412: ldc 15 ("null") 
;             1414: invokevirtual 150 (java/lang/String/concat (Ljava/lang/String;)Ljava/lang/String;) 
;             1417: dup 
;             1418: ifnull 6 
;             1421: goto 6 
;             1424: pop 
;             1425: ldc 15 ("null") 
;             1427: new 117 (java/lang/Integer) 
;             1430: dup 
;             1431: iload_3 
;             1432: invokespecial 61 (java/lang/Integer/<init> (I)V) 
;             1435: invokevirtual 27 (java/lang/Integer/toString ()Ljava/lang/String;) 
;             1438: invokevirtual 150 (java/lang/String/concat (Ljava/lang/String;)Ljava/lang/String;) 
;             1441: dup 
;             1442: ifnull 6 
;             1445: goto 6 
;             1448: pop 
;             1449: ldc 15 ("null") 
;             1451: ldc 1 (" treasure(s) and ") 
;             1453: dup 
;             1454: ifnull 6 
;             1457: goto 6 
;             1460: pop 
;             1461: ldc 15 ("null") 
;             1463: invokevirtual 150 (java/lang/String/concat (Ljava/lang/String;)Ljava/lang/String;) 
;             1466: dup 
;             1467: ifnull 6 
;             1470: goto 6 
;             1473: pop 
;             1474: ldc 15 ("null") 
;             1476: new 117 (java/lang/Integer) 
;             1479: dup 
;             1480: iload_2 
;             1481: invokespecial 61 (java/lang/Integer/<init> (I)V) 
;             1484: invokevirtual 27 (java/lang/Integer/toString ()Ljava/lang/String;) 
;             1487: invokevirtual 150 (java/lang/String/concat (Ljava/lang/String;)Ljava/lang/String;) 
;             1490: dup 
;             1491: ifnull 6 
;             1494: goto 6 
;             1497: pop 
;             1498: ldc 15 ("null") 
;             1500: ldc 142 (" coin(s).") 
;             1502: dup 
;             1503: ifnull 6 
;             1506: goto 6 
;             1509: pop 
;             1510: ldc 15 ("null") 
;             1512: invokevirtual 150 (java/lang/String/concat (Ljava/lang/String;)Ljava/lang/String;) 
;             1515: invokevirtual 8 (joos/lib/JoosIO/println (Ljava/lang/String;)V) 
;             1518: aload_1 
;             1519: aload 9 
;             1521: dup 
;             1522: ifnull 6 
;             1525: goto 6 
;             1528: pop 
;             1529: ldc 15 ("null") 
;             1531: ldc 139 (" has ") 
;             1533: dup 
;             1534: ifnull 6 
;             1537: goto 6 
;             1540: pop 
;             1541: ldc 15 ("null") 
;             1543: invokevirtual 150 (java/lang/String/concat (Ljava/lang/String;)Ljava/lang/String;) 
;             1546: dup 
;             1547: ifnull 6 
;             1550: goto 6 
;             1553: pop 
;             1554: ldc 15 ("null") 
;             1556: new 117 (java/lang/Integer) 
;             1559: dup 
;             1560: iload 4 
;             1562: invokespecial 61 (java/lang/Integer/<init> (I)V) 
;             1565: invokevirtual 27 (java/lang/Integer/toString ()Ljava/lang/String;) 
;             1568: invokevirtual 150 (java/lang/String/concat (Ljava/lang/String;)Ljava/lang/String;) 
;             1571: dup 
;             1572: ifnull 6 
;             1575: goto 6 
;             1578: pop 
;             1579: ldc 15 ("null") 
;             1581: ldc 101 (" hit points remaining.") 
;             1583: dup 
;             1584: ifnull 6 
;             1587: goto 6 
;             1590: pop 
;             1591: ldc 15 ("null") 
;             1593: invokevirtual 150 (java/lang/String/concat (Ljava/lang/String;)Ljava/lang/String;) 
;             1596: invokevirtual 8 (joos/lib/JoosIO/println (Ljava/lang/String;)V) 
;             1599: aload_1 
;             1600: ldc 38 ("Thank you for playing\n") 
;             1602: dup 
;             1603: ifnull 6 
;             1606: goto 6 
;             1609: pop 
;             1610: ldc 15 ("null") 
;             1612: aload 11 
;             1614: dup 
;             1615: ifnull 6 
;             1618: goto 6 
;             1621: pop 
;             1622: ldc 15 ("null") 
;             1624: invokevirtual 150 (java/lang/String/concat (Ljava/lang/String;)Ljava/lang/String;) 
;             1627: invokevirtual 8 (joos/lib/JoosIO/println (Ljava/lang/String;)V) 
;             1630: return 
;         exception_table_length 0
;         attributes_count 0



; attributes_count 1

; class_attributes[0] (offset 0xdfa) :
;     name_index 131 (SourceFile)
;     attribute_length 2
;     sourcefile_index 78

; End of file reached successfully. Enjoy :)
