; magic number 0xCAFEBABE
; bytecode version 45.3

; constant pool count 283
; cp[1] (offset 0xd) -> CONSTANT_String 169
; cp[2] (offset 0x10) -> CONSTANT_String 170
; cp[3] (offset 0x17) -> CONSTANT_Utf8 "(I)C"
; cp[4] (offset 0x1a) -> CONSTANT_String 171
; cp[5] (offset 0x1d) -> CONSTANT_String 172
; cp[6] (offset 0x20) -> CONSTANT_String 173
; cp[7] (offset 0x23) -> CONSTANT_String 174
; cp[8] (offset 0x26) -> CONSTANT_String 175
; cp[9] (offset 0x29) -> CONSTANT_String 177
; cp[10] (offset 0x2c) -> CONSTANT_String 178
; cp[11] (offset 0x37) -> CONSTANT_Utf8 "intValue"
; cp[12] (offset 0x3a) -> CONSTANT_String 179
; cp[13] (offset 0x3d) -> CONSTANT_String 181
; cp[14] (offset 0x40) -> CONSTANT_String 183
; cp[15] (offset 0x43) -> CONSTANT_String 185
; cp[16] (offset 0x46) -> CONSTANT_String 188
; cp[17] (offset 0x49) -> CONSTANT_String 190
; cp[18] (offset 0x4c) -> CONSTANT_String 192
; cp[19] (offset 0x59) -> CONSTANT_Utf8 "addElement"
; cp[20] (offset 0x5c) -> CONSTANT_String 194
; cp[21] (offset 0x5f) -> CONSTANT_Class 113
; cp[22] (offset 0x62) -> CONSTANT_String 196
; cp[23] (offset 0x65) -> CONSTANT_String 135
; cp[24] (offset 0x68) -> CONSTANT_String 198
; cp[25] (offset 0x6b) -> CONSTANT_String 136
; cp[26] (offset 0x6e) -> CONSTANT_String 200
; cp[27] (offset 0x71) -> CONSTANT_String 137
; cp[28] (offset 0x74) -> CONSTANT_String 138
; cp[29] (offset 0x77) -> CONSTANT_String 139
; cp[30] (offset 0x7a) -> CONSTANT_String 140
; cp[31] (offset 0x7d) -> CONSTANT_String 141
; cp[32] (offset 0x80) -> CONSTANT_String 142
; cp[33] (offset 0x83) -> CONSTANT_String 144
; cp[34] (offset 0x86) -> CONSTANT_String 203
; cp[35] (offset 0x89) -> CONSTANT_String 145
; cp[36] (offset 0x8c) -> CONSTANT_String 204
; cp[37] (offset 0x8f) -> CONSTANT_String 206
; cp[38] (offset 0x92) -> CONSTANT_String 207
; cp[39] (offset 0x95) -> CONSTANT_String 208
; cp[40] (offset 0x98) -> CONSTANT_String 209
; cp[41] (offset 0x9b) -> CONSTANT_String 210
; cp[42] (offset 0x9e) -> CONSTANT_String 211
; cp[43] (offset 0xa4) -> CONSTANT_Utf8 "()V"
; cp[44] (offset 0xa7) -> CONSTANT_String 212
; cp[45] (offset 0xaa) -> CONSTANT_String 213
; cp[46] (offset 0xad) -> CONSTANT_String 214
; cp[47] (offset 0xb0) -> CONSTANT_String 215
; cp[48] (offset 0xb3) -> CONSTANT_String 216
; cp[49] (offset 0xb6) -> CONSTANT_String 217
; cp[50] (offset 0xb9) -> CONSTANT_String 218
; cp[51] (offset 0xbc) -> CONSTANT_Class 114
; cp[52] (offset 0xbf) -> CONSTANT_String 220
; cp[53] (offset 0xc2) -> CONSTANT_String 222
; cp[54] (offset 0xc7) -> CONSTANT_Fieldref 21, 268
; cp[55] (offset 0xca) -> CONSTANT_String 224
; cp[56] (offset 0xcd) -> CONSTANT_String 226
; cp[57] (offset 0xd0) -> CONSTANT_String 228
; cp[58] (offset 0xd3) -> CONSTANT_String 230
; cp[59] (offset 0xd9) -> CONSTANT_Utf8 "()I"
; cp[60] (offset 0xdc) -> CONSTANT_String 232
; cp[61] (offset 0xdf) -> CONSTANT_String 234
; cp[62] (offset 0xe2) -> CONSTANT_String 150
; cp[63] (offset 0xe5) -> CONSTANT_String 236
; cp[64] (offset 0xe8) -> CONSTANT_String 151
; cp[65] (offset 0xeb) -> CONSTANT_String 238
; cp[66] (offset 0xee) -> CONSTANT_String 152
; cp[67] (offset 0xf1) -> CONSTANT_String 239
; cp[68] (offset 0xf4) -> CONSTANT_String 154
; cp[69] (offset 0xf7) -> CONSTANT_String 156
; cp[70] (offset 0xfa) -> CONSTANT_String 157
; cp[71] (offset 0xfd) -> CONSTANT_String 158
; cp[72] (offset 0x100) -> CONSTANT_String 159
; cp[73] (offset 0x103) -> CONSTANT_String 160
; cp[74] (offset 0x106) -> CONSTANT_String 161
; cp[75] (offset 0x109) -> CONSTANT_String 240
; cp[76] (offset 0x10c) -> CONSTANT_String 241
; cp[77] (offset 0x10f) -> CONSTANT_String 242
; cp[78] (offset 0x112) -> CONSTANT_String 243
; cp[79] (offset 0x115) -> CONSTANT_String 244
; cp[80] (offset 0x118) -> CONSTANT_String 246
; cp[81] (offset 0x11b) -> CONSTANT_String 247
; cp[82] (offset 0x11e) -> CONSTANT_String 248
; cp[83] (offset 0x121) -> CONSTANT_String 249
; cp[84] (offset 0x124) -> CONSTANT_String 250
; cp[85] (offset 0x127) -> CONSTANT_String 251
; cp[86] (offset 0x13f) -> CONSTANT_Utf8 "(Ljava/lang/String;)V"
; cp[87] (offset 0x142) -> CONSTANT_String 254
; cp[88] (offset 0x147) -> CONSTANT_NameAndType 147, 3
; cp[89] (offset 0x14a) -> CONSTANT_String 180
; cp[90] (offset 0x14d) -> CONSTANT_String 182
; cp[91] (offset 0x150) -> CONSTANT_String 184
; cp[92] (offset 0x153) -> CONSTANT_String 187
; cp[93] (offset 0x156) -> CONSTANT_String 189
; cp[94] (offset 0x159) -> CONSTANT_String 191
; cp[95] (offset 0x15c) -> CONSTANT_String 193
; cp[96] (offset 0x15f) -> CONSTANT_String 195
; cp[97] (offset 0x162) -> CONSTANT_String 197
; cp[98] (offset 0x165) -> CONSTANT_String 199
; cp[99] (offset 0x16d) -> CONSTANT_Utf8 "get64"
; cp[100] (offset 0x172) -> CONSTANT_Methodref 149, 127
; cp[101] (offset 0x175) -> CONSTANT_String 219
; cp[102] (offset 0x17a) -> CONSTANT_Methodref 110, 148
; cp[103] (offset 0x17d) -> CONSTANT_String 221
; cp[104] (offset 0x180) -> CONSTANT_String 223
; cp[105] (offset 0x183) -> CONSTANT_String 225
; cp[106] (offset 0x186) -> CONSTANT_String 227
; cp[107] (offset 0x189) -> CONSTANT_String 229
; cp[108] (offset 0x18c) -> CONSTANT_String 231
; cp[109] (offset 0x18f) -> CONSTANT_String 233
; cp[110] (offset 0x192) -> CONSTANT_Class 155
; cp[111] (offset 0x195) -> CONSTANT_String 235
; cp[112] (offset 0x198) -> CONSTANT_String 237
; cp[113] (offset 0x1a5) -> CONSTANT_Utf8 "Conversion"
; cp[114] (offset 0x1b8) -> CONSTANT_Utf8 "java/lang/String"
; cp[115] (offset 0x1bd) -> CONSTANT_Methodref 176, 264
; cp[116] (offset 0x1c0) -> CONSTANT_String 252
; cp[117] (offset 0x1c3) -> CONSTANT_String 253
; cp[118] (offset 0x1c6) -> CONSTANT_String 255
; cp[119] (offset 0x1c9) -> CONSTANT_String 256
; cp[120] (offset 0x1cc) -> CONSTANT_String 257
; cp[121] (offset 0x1cf) -> CONSTANT_String 258
; cp[122] (offset 0x1d2) -> CONSTANT_String 259
; cp[123] (offset 0x1d5) -> CONSTANT_String 261
; cp[124] (offset 0x1d8) -> CONSTANT_String 262
; cp[125] (offset 0x1db) -> CONSTANT_String 263
; cp[126] (offset 0x1ea) -> CONSTANT_Utf8 "Conversion.j"
; cp[127] (offset 0x1ef) -> CONSTANT_NameAndType 270, 134
; cp[128] (offset 0x1f4) -> CONSTANT_Methodref 149, 269
; cp[129] (offset 0x1f9) -> CONSTANT_Utf8 "63"
; cp[130] (offset 0x1fe) -> CONSTANT_Utf8 "62"
; cp[131] (offset 0x203) -> CONSTANT_Utf8 "61"
; cp[132] (offset 0x208) -> CONSTANT_Utf8 "60"
; cp[133] (offset 0x215) -> CONSTANT_Utf8 "base64_key"
; cp[134] (offset 0x22d) -> CONSTANT_Utf8 "(I)Ljava/lang/Object;"
; cp[135] (offset 0x232) -> CONSTANT_Utf8 "59"
; cp[136] (offset 0x237) -> CONSTANT_Utf8 "58"
; cp[137] (offset 0x23c) -> CONSTANT_Utf8 "57"
; cp[138] (offset 0x241) -> CONSTANT_Utf8 "56"
; cp[139] (offset 0x246) -> CONSTANT_Utf8 "55"
; cp[140] (offset 0x24b) -> CONSTANT_Utf8 "54"
; cp[141] (offset 0x250) -> CONSTANT_Utf8 "53"
; cp[142] (offset 0x255) -> CONSTANT_Utf8 "52"
; cp[143] (offset 0x26d) -> CONSTANT_Utf8 "(Ljava/lang/Object;)V"
; cp[144] (offset 0x272) -> CONSTANT_Utf8 "51"
; cp[145] (offset 0x277) -> CONSTANT_Utf8 "50"
; cp[146] (offset 0x27c) -> CONSTANT_NameAndType 133, 266
; cp[147] (offset 0x285) -> CONSTANT_Utf8 "charAt"
; cp[148] (offset 0x28a) -> CONSTANT_NameAndType 186, 43
; cp[149] (offset 0x28d) -> CONSTANT_Class 245
; cp[150] (offset 0x292) -> CONSTANT_Utf8 "49"
; cp[151] (offset 0x297) -> CONSTANT_Utf8 "48"
; cp[152] (offset 0x29c) -> CONSTANT_Utf8 "47"
; cp[153] (offset 0x2a3) -> CONSTANT_Utf8 "Code"
; cp[154] (offset 0x2a8) -> CONSTANT_Utf8 "46"
; cp[155] (offset 0x2bb) -> CONSTANT_Utf8 "java/lang/Object"
; cp[156] (offset 0x2c0) -> CONSTANT_Utf8 "45"
; cp[157] (offset 0x2c5) -> CONSTANT_Utf8 "44"
; cp[158] (offset 0x2ca) -> CONSTANT_Utf8 "43"
; cp[159] (offset 0x2cf) -> CONSTANT_Utf8 "42"
; cp[160] (offset 0x2d4) -> CONSTANT_Utf8 "41"
; cp[161] (offset 0x2d9) -> CONSTANT_Utf8 "40"
; cp[162] (offset 0x2dd) -> CONSTANT_Utf8 "z"
; cp[163] (offset 0x2e1) -> CONSTANT_Utf8 "y"
; cp[164] (offset 0x2e5) -> CONSTANT_Utf8 "x"
; cp[165] (offset 0x2e9) -> CONSTANT_Utf8 "w"
; cp[166] (offset 0x2f1) -> CONSTANT_Utf8 "get10"
; cp[167] (offset 0x2f5) -> CONSTANT_Utf8 "v"
; cp[168] (offset 0x2f9) -> CONSTANT_Utf8 "u"
; cp[169] (offset 0x2fd) -> CONSTANT_Utf8 "t"
; cp[170] (offset 0x301) -> CONSTANT_Utf8 "s"
; cp[171] (offset 0x305) -> CONSTANT_Utf8 "r"
; cp[172] (offset 0x309) -> CONSTANT_Utf8 "q"
; cp[173] (offset 0x30d) -> CONSTANT_Utf8 "p"
; cp[174] (offset 0x311) -> CONSTANT_Utf8 "o"
; cp[175] (offset 0x315) -> CONSTANT_Utf8 "n"
; cp[176] (offset 0x318) -> CONSTANT_Class 265
; cp[177] (offset 0x31c) -> CONSTANT_Utf8 "m"
; cp[178] (offset 0x320) -> CONSTANT_Utf8 "l"
; cp[179] (offset 0x324) -> CONSTANT_Utf8 "k"
; cp[180] (offset 0x329) -> CONSTANT_Utf8 "39"
; cp[181] (offset 0x32d) -> CONSTANT_Utf8 "j"
; cp[182] (offset 0x332) -> CONSTANT_Utf8 "38"
; cp[183] (offset 0x336) -> CONSTANT_Utf8 "i"
; cp[184] (offset 0x33b) -> CONSTANT_Utf8 "37"
; cp[185] (offset 0x33f) -> CONSTANT_Utf8 "h"
; cp[186] (offset 0x348) -> CONSTANT_Utf8 "<init>"
; cp[187] (offset 0x34d) -> CONSTANT_Utf8 "36"
; cp[188] (offset 0x351) -> CONSTANT_Utf8 "g"
; cp[189] (offset 0x356) -> CONSTANT_Utf8 "35"
; cp[190] (offset 0x35a) -> CONSTANT_Utf8 "f"
; cp[191] (offset 0x35f) -> CONSTANT_Utf8 "34"
; cp[192] (offset 0x363) -> CONSTANT_Utf8 "e"
; cp[193] (offset 0x368) -> CONSTANT_Utf8 "33"
; cp[194] (offset 0x36c) -> CONSTANT_Utf8 "d"
; cp[195] (offset 0x371) -> CONSTANT_Utf8 "32"
; cp[196] (offset 0x375) -> CONSTANT_Utf8 "c"
; cp[197] (offset 0x37a) -> CONSTANT_Utf8 "31"
; cp[198] (offset 0x37e) -> CONSTANT_Utf8 "b"
; cp[199] (offset 0x383) -> CONSTANT_Utf8 "30"
; cp[200] (offset 0x387) -> CONSTANT_Utf8 "a"
; cp[201] (offset 0x394) -> CONSTANT_Utf8 "SourceFile"
; cp[202] (offset 0x399) -> CONSTANT_Methodref 51, 88
; cp[203] (offset 0x39d) -> CONSTANT_Utf8 "Z"
; cp[204] (offset 0x3a1) -> CONSTANT_Utf8 "Y"
; cp[205] (offset 0x3a6) -> CONSTANT_Methodref 176, 271
; cp[206] (offset 0x3aa) -> CONSTANT_Utf8 "X"
; cp[207] (offset 0x3ae) -> CONSTANT_Utf8 "W"
; cp[208] (offset 0x3b2) -> CONSTANT_Utf8 "V"
; cp[209] (offset 0x3b6) -> CONSTANT_Utf8 "U"
; cp[210] (offset 0x3ba) -> CONSTANT_Utf8 "T"
; cp[211] (offset 0x3be) -> CONSTANT_Utf8 "S"
; cp[212] (offset 0x3c2) -> CONSTANT_Utf8 "R"
; cp[213] (offset 0x3c6) -> CONSTANT_Utf8 "Q"
; cp[214] (offset 0x3ca) -> CONSTANT_Utf8 "P"
; cp[215] (offset 0x3ce) -> CONSTANT_Utf8 "O"
; cp[216] (offset 0x3d2) -> CONSTANT_Utf8 "N"
; cp[217] (offset 0x3d6) -> CONSTANT_Utf8 "M"
; cp[218] (offset 0x3da) -> CONSTANT_Utf8 "L"
; cp[219] (offset 0x3df) -> CONSTANT_Utf8 "29"
; cp[220] (offset 0x3e3) -> CONSTANT_Utf8 "K"
; cp[221] (offset 0x3e8) -> CONSTANT_Utf8 "28"
; cp[222] (offset 0x3ec) -> CONSTANT_Utf8 "J"
; cp[223] (offset 0x3f1) -> CONSTANT_Utf8 "27"
; cp[224] (offset 0x3f5) -> CONSTANT_Utf8 "I"
; cp[225] (offset 0x3fa) -> CONSTANT_Utf8 "26"
; cp[226] (offset 0x3fe) -> CONSTANT_Utf8 "H"
; cp[227] (offset 0x403) -> CONSTANT_Utf8 "25"
; cp[228] (offset 0x407) -> CONSTANT_Utf8 "G"
; cp[229] (offset 0x40c) -> CONSTANT_Utf8 "24"
; cp[230] (offset 0x410) -> CONSTANT_Utf8 "F"
; cp[231] (offset 0x415) -> CONSTANT_Utf8 "23"
; cp[232] (offset 0x419) -> CONSTANT_Utf8 "E"
; cp[233] (offset 0x41e) -> CONSTANT_Utf8 "22"
; cp[234] (offset 0x422) -> CONSTANT_Utf8 "D"
; cp[235] (offset 0x427) -> CONSTANT_Utf8 "21"
; cp[236] (offset 0x42b) -> CONSTANT_Utf8 "C"
; cp[237] (offset 0x430) -> CONSTANT_Utf8 "20"
; cp[238] (offset 0x434) -> CONSTANT_Utf8 "B"
; cp[239] (offset 0x438) -> CONSTANT_Utf8 "A"
; cp[240] (offset 0x43c) -> CONSTANT_Utf8 "9"
; cp[241] (offset 0x440) -> CONSTANT_Utf8 "8"
; cp[242] (offset 0x444) -> CONSTANT_Utf8 "7"
; cp[243] (offset 0x448) -> CONSTANT_Utf8 "6"
; cp[244] (offset 0x44c) -> CONSTANT_Utf8 "5"
; cp[245] (offset 0x45f) -> CONSTANT_Utf8 "java/util/Vector"
; cp[246] (offset 0x463) -> CONSTANT_Utf8 "4"
; cp[247] (offset 0x467) -> CONSTANT_Utf8 "3"
; cp[248] (offset 0x46b) -> CONSTANT_Utf8 "2"
; cp[249] (offset 0x46f) -> CONSTANT_Utf8 "1"
; cp[250] (offset 0x473) -> CONSTANT_Utf8 "0"
; cp[251] (offset 0x477) -> CONSTANT_Utf8 "/"
; cp[252] (offset 0x47c) -> CONSTANT_Utf8 "19"
; cp[253] (offset 0x481) -> CONSTANT_Utf8 "18"
; cp[254] (offset 0x485) -> CONSTANT_Utf8 "+"
; cp[255] (offset 0x48a) -> CONSTANT_Utf8 "17"
; cp[256] (offset 0x48f) -> CONSTANT_Utf8 "16"
; cp[257] (offset 0x494) -> CONSTANT_Utf8 "15"
; cp[258] (offset 0x499) -> CONSTANT_Utf8 "14"
; cp[259] (offset 0x49e) -> CONSTANT_Utf8 "13"
; cp[260] (offset 0x4a3) -> CONSTANT_Methodref 149, 148
; cp[261] (offset 0x4a8) -> CONSTANT_Utf8 "12"
; cp[262] (offset 0x4ad) -> CONSTANT_Utf8 "11"
; cp[263] (offset 0x4b2) -> CONSTANT_Utf8 "10"
; cp[264] (offset 0x4b7) -> CONSTANT_NameAndType 186, 86
; cp[265] (offset 0x4cb) -> CONSTANT_Utf8 "java/lang/Integer"
; cp[266] (offset 0x4e0) -> CONSTANT_Utf8 "Ljava/util/Vector;"
; cp[267] (offset 0x4e5) -> CONSTANT_Fieldref 21, 146
; cp[268] (offset 0x4ea) -> CONSTANT_NameAndType 276, 266
; cp[269] (offset 0x4ef) -> CONSTANT_NameAndType 19, 143
; cp[270] (offset 0x4fb) -> CONSTANT_Utf8 "elementAt"
; cp[271] (offset 0x500) -> CONSTANT_NameAndType 11, 59
; cp[272] (offset 0x503) -> CONSTANT_String 129
; cp[273] (offset 0x506) -> CONSTANT_String 130
; cp[274] (offset 0x509) -> CONSTANT_String 162
; cp[275] (offset 0x50c) -> CONSTANT_String 131
; cp[276] (offset 0x51a) -> CONSTANT_Utf8 "base64_to10"
; cp[277] (offset 0x51d) -> CONSTANT_String 163
; cp[278] (offset 0x520) -> CONSTANT_String 132
; cp[279] (offset 0x523) -> CONSTANT_String 164
; cp[280] (offset 0x526) -> CONSTANT_String 165
; cp[281] (offset 0x529) -> CONSTANT_String 167
; cp[282] (offset 0x52c) -> CONSTANT_String 168

; access flags = 0x21 [ ACC_SUPER ACC_PUBLIC ]
; this_class index = 21
; super_class index = 110

; interfaces_count = 0


; fields_count = 2

; fields[0] (offset 0x536) :
;     access_flags 0x4 [ ACC_PROTECTED ]
;     name_index 133 (base64_key)
;     descriptor_index 266 (Ljava/util/Vector;)
;     attributes_count 0

; fields[1] (offset 0x53e) :
;     access_flags 0x4 [ ACC_PROTECTED ]
;     name_index 276 (base64_to10)
;     descriptor_index 266 (Ljava/util/Vector;)
;     attributes_count 0

; methods_count 3

; methods[0] (offset 0x548) :
;     access_flags 0x1 [ ACC_PUBLIC ]
;     name_index 186 (<init>)
;     descriptor_index 43 (()V)
;     attributes_count 1
;     method_attributes[0] :
;         name_index 153 (Code)
;         attribute_length 1738
;         max_stack 3
;         max_locals 1
;         code_length 1726
;         code :
;                0: aload_0 
;                1: invokespecial 102 (java/lang/Object/<init> ()V) 
;                4: new 149 (java/util/Vector) 
;                7: dup 
;                8: invokespecial 260 (java/util/Vector/<init> ()V) 
;               11: dup 
;               12: aload_0 
;               13: swap 
;               14: putfield 267 (Conversion/base64_key Ljava/util/Vector;) 
;               17: pop 
;               18: aload_0 
;               19: getfield 267 (Conversion/base64_key Ljava/util/Vector;) 
;               22: ldc 67 ("A") 
;               24: invokevirtual 128 (java/util/Vector/addElement (Ljava/lang/Object;)V) 
;               27: aload_0 
;               28: getfield 267 (Conversion/base64_key Ljava/util/Vector;) 
;               31: ldc 65 ("B") 
;               33: invokevirtual 128 (java/util/Vector/addElement (Ljava/lang/Object;)V) 
;               36: aload_0 
;               37: getfield 267 (Conversion/base64_key Ljava/util/Vector;) 
;               40: ldc 63 ("C") 
;               42: invokevirtual 128 (java/util/Vector/addElement (Ljava/lang/Object;)V) 
;               45: aload_0 
;               46: getfield 267 (Conversion/base64_key Ljava/util/Vector;) 
;               49: ldc 61 ("D") 
;               51: invokevirtual 128 (java/util/Vector/addElement (Ljava/lang/Object;)V) 
;               54: aload_0 
;               55: getfield 267 (Conversion/base64_key Ljava/util/Vector;) 
;               58: ldc 60 ("E") 
;               60: invokevirtual 128 (java/util/Vector/addElement (Ljava/lang/Object;)V) 
;               63: aload_0 
;               64: getfield 267 (Conversion/base64_key Ljava/util/Vector;) 
;               67: ldc 58 ("F") 
;               69: invokevirtual 128 (java/util/Vector/addElement (Ljava/lang/Object;)V) 
;               72: aload_0 
;               73: getfield 267 (Conversion/base64_key Ljava/util/Vector;) 
;               76: ldc 57 ("G") 
;               78: invokevirtual 128 (java/util/Vector/addElement (Ljava/lang/Object;)V) 
;               81: aload_0 
;               82: getfield 267 (Conversion/base64_key Ljava/util/Vector;) 
;               85: ldc 56 ("H") 
;               87: invokevirtual 128 (java/util/Vector/addElement (Ljava/lang/Object;)V) 
;               90: aload_0 
;               91: getfield 267 (Conversion/base64_key Ljava/util/Vector;) 
;               94: ldc 55 ("I") 
;               96: invokevirtual 128 (java/util/Vector/addElement (Ljava/lang/Object;)V) 
;               99: aload_0 
;              100: getfield 267 (Conversion/base64_key Ljava/util/Vector;) 
;              103: ldc 53 ("J") 
;              105: invokevirtual 128 (java/util/Vector/addElement (Ljava/lang/Object;)V) 
;              108: aload_0 
;              109: getfield 267 (Conversion/base64_key Ljava/util/Vector;) 
;              112: ldc 52 ("K") 
;              114: invokevirtual 128 (java/util/Vector/addElement (Ljava/lang/Object;)V) 
;              117: aload_0 
;              118: getfield 267 (Conversion/base64_key Ljava/util/Vector;) 
;              121: ldc 50 ("L") 
;              123: invokevirtual 128 (java/util/Vector/addElement (Ljava/lang/Object;)V) 
;              126: aload_0 
;              127: getfield 267 (Conversion/base64_key Ljava/util/Vector;) 
;              130: ldc 49 ("M") 
;              132: invokevirtual 128 (java/util/Vector/addElement (Ljava/lang/Object;)V) 
;              135: aload_0 
;              136: getfield 267 (Conversion/base64_key Ljava/util/Vector;) 
;              139: ldc 48 ("N") 
;              141: invokevirtual 128 (java/util/Vector/addElement (Ljava/lang/Object;)V) 
;              144: aload_0 
;              145: getfield 267 (Conversion/base64_key Ljava/util/Vector;) 
;              148: ldc 47 ("O") 
;              150: invokevirtual 128 (java/util/Vector/addElement (Ljava/lang/Object;)V) 
;              153: aload_0 
;              154: getfield 267 (Conversion/base64_key Ljava/util/Vector;) 
;              157: ldc 46 ("P") 
;              159: invokevirtual 128 (java/util/Vector/addElement (Ljava/lang/Object;)V) 
;              162: aload_0 
;              163: getfield 267 (Conversion/base64_key Ljava/util/Vector;) 
;              166: ldc 45 ("Q") 
;              168: invokevirtual 128 (java/util/Vector/addElement (Ljava/lang/Object;)V) 
;              171: aload_0 
;              172: getfield 267 (Conversion/base64_key Ljava/util/Vector;) 
;              175: ldc 44 ("R") 
;              177: invokevirtual 128 (java/util/Vector/addElement (Ljava/lang/Object;)V) 
;              180: aload_0 
;              181: getfield 267 (Conversion/base64_key Ljava/util/Vector;) 
;              184: ldc 42 ("S") 
;              186: invokevirtual 128 (java/util/Vector/addElement (Ljava/lang/Object;)V) 
;              189: aload_0 
;              190: getfield 267 (Conversion/base64_key Ljava/util/Vector;) 
;              193: ldc 41 ("T") 
;              195: invokevirtual 128 (java/util/Vector/addElement (Ljava/lang/Object;)V) 
;              198: aload_0 
;              199: getfield 267 (Conversion/base64_key Ljava/util/Vector;) 
;              202: ldc 40 ("U") 
;              204: invokevirtual 128 (java/util/Vector/addElement (Ljava/lang/Object;)V) 
;              207: aload_0 
;              208: getfield 267 (Conversion/base64_key Ljava/util/Vector;) 
;              211: ldc 39 ("V") 
;              213: invokevirtual 128 (java/util/Vector/addElement (Ljava/lang/Object;)V) 
;              216: aload_0 
;              217: getfield 267 (Conversion/base64_key Ljava/util/Vector;) 
;              220: ldc 38 ("W") 
;              222: invokevirtual 128 (java/util/Vector/addElement (Ljava/lang/Object;)V) 
;              225: aload_0 
;              226: getfield 267 (Conversion/base64_key Ljava/util/Vector;) 
;              229: ldc 37 ("X") 
;              231: invokevirtual 128 (java/util/Vector/addElement (Ljava/lang/Object;)V) 
;              234: aload_0 
;              235: getfield 267 (Conversion/base64_key Ljava/util/Vector;) 
;              238: ldc 36 ("Y") 
;              240: invokevirtual 128 (java/util/Vector/addElement (Ljava/lang/Object;)V) 
;              243: aload_0 
;              244: getfield 267 (Conversion/base64_key Ljava/util/Vector;) 
;              247: ldc 34 ("Z") 
;              249: invokevirtual 128 (java/util/Vector/addElement (Ljava/lang/Object;)V) 
;              252: aload_0 
;              253: getfield 267 (Conversion/base64_key Ljava/util/Vector;) 
;              256: ldc 26 ("a") 
;              258: invokevirtual 128 (java/util/Vector/addElement (Ljava/lang/Object;)V) 
;              261: aload_0 
;              262: getfield 267 (Conversion/base64_key Ljava/util/Vector;) 
;              265: ldc 24 ("b") 
;              267: invokevirtual 128 (java/util/Vector/addElement (Ljava/lang/Object;)V) 
;              270: aload_0 
;              271: getfield 267 (Conversion/base64_key Ljava/util/Vector;) 
;              274: ldc 22 ("c") 
;              276: invokevirtual 128 (java/util/Vector/addElement (Ljava/lang/Object;)V) 
;              279: aload_0 
;              280: getfield 267 (Conversion/base64_key Ljava/util/Vector;) 
;              283: ldc 20 ("d") 
;              285: invokevirtual 128 (java/util/Vector/addElement (Ljava/lang/Object;)V) 
;              288: aload_0 
;              289: getfield 267 (Conversion/base64_key Ljava/util/Vector;) 
;              292: ldc 18 ("e") 
;              294: invokevirtual 128 (java/util/Vector/addElement (Ljava/lang/Object;)V) 
;              297: aload_0 
;              298: getfield 267 (Conversion/base64_key Ljava/util/Vector;) 
;              301: ldc 17 ("f") 
;              303: invokevirtual 128 (java/util/Vector/addElement (Ljava/lang/Object;)V) 
;              306: aload_0 
;              307: getfield 267 (Conversion/base64_key Ljava/util/Vector;) 
;              310: ldc 16 ("g") 
;              312: invokevirtual 128 (java/util/Vector/addElement (Ljava/lang/Object;)V) 
;              315: aload_0 
;              316: getfield 267 (Conversion/base64_key Ljava/util/Vector;) 
;              319: ldc 15 ("h") 
;              321: invokevirtual 128 (java/util/Vector/addElement (Ljava/lang/Object;)V) 
;              324: aload_0 
;              325: getfield 267 (Conversion/base64_key Ljava/util/Vector;) 
;              328: ldc 14 ("i") 
;              330: invokevirtual 128 (java/util/Vector/addElement (Ljava/lang/Object;)V) 
;              333: aload_0 
;              334: getfield 267 (Conversion/base64_key Ljava/util/Vector;) 
;              337: ldc 13 ("j") 
;              339: invokevirtual 128 (java/util/Vector/addElement (Ljava/lang/Object;)V) 
;              342: aload_0 
;              343: getfield 267 (Conversion/base64_key Ljava/util/Vector;) 
;              346: ldc 12 ("k") 
;              348: invokevirtual 128 (java/util/Vector/addElement (Ljava/lang/Object;)V) 
;              351: aload_0 
;              352: getfield 267 (Conversion/base64_key Ljava/util/Vector;) 
;              355: ldc 10 ("l") 
;              357: invokevirtual 128 (java/util/Vector/addElement (Ljava/lang/Object;)V) 
;              360: aload_0 
;              361: getfield 267 (Conversion/base64_key Ljava/util/Vector;) 
;              364: ldc 9 ("m") 
;              366: invokevirtual 128 (java/util/Vector/addElement (Ljava/lang/Object;)V) 
;              369: aload_0 
;              370: getfield 267 (Conversion/base64_key Ljava/util/Vector;) 
;              373: ldc 8 ("n") 
;              375: invokevirtual 128 (java/util/Vector/addElement (Ljava/lang/Object;)V) 
;              378: aload_0 
;              379: getfield 267 (Conversion/base64_key Ljava/util/Vector;) 
;              382: ldc 7 ("o") 
;              384: invokevirtual 128 (java/util/Vector/addElement (Ljava/lang/Object;)V) 
;              387: aload_0 
;              388: getfield 267 (Conversion/base64_key Ljava/util/Vector;) 
;              391: ldc 6 ("p") 
;              393: invokevirtual 128 (java/util/Vector/addElement (Ljava/lang/Object;)V) 
;              396: aload_0 
;              397: getfield 267 (Conversion/base64_key Ljava/util/Vector;) 
;              400: ldc 5 ("q") 
;              402: invokevirtual 128 (java/util/Vector/addElement (Ljava/lang/Object;)V) 
;              405: aload_0 
;              406: getfield 267 (Conversion/base64_key Ljava/util/Vector;) 
;              409: ldc 4 ("r") 
;              411: invokevirtual 128 (java/util/Vector/addElement (Ljava/lang/Object;)V) 
;              414: aload_0 
;              415: getfield 267 (Conversion/base64_key Ljava/util/Vector;) 
;              418: ldc 2 ("s") 
;              420: invokevirtual 128 (java/util/Vector/addElement (Ljava/lang/Object;)V) 
;              423: aload_0 
;              424: getfield 267 (Conversion/base64_key Ljava/util/Vector;) 
;              427: ldc 1 ("t") 
;              429: invokevirtual 128 (java/util/Vector/addElement (Ljava/lang/Object;)V) 
;              432: aload_0 
;              433: getfield 267 (Conversion/base64_key Ljava/util/Vector;) 
;              436: ldc_w 282 ("u") 
;              439: invokevirtual 128 (java/util/Vector/addElement (Ljava/lang/Object;)V) 
;              442: aload_0 
;              443: getfield 267 (Conversion/base64_key Ljava/util/Vector;) 
;              446: ldc_w 281 ("v") 
;              449: invokevirtual 128 (java/util/Vector/addElement (Ljava/lang/Object;)V) 
;              452: aload_0 
;              453: getfield 267 (Conversion/base64_key Ljava/util/Vector;) 
;              456: ldc_w 280 ("w") 
;              459: invokevirtual 128 (java/util/Vector/addElement (Ljava/lang/Object;)V) 
;              462: aload_0 
;              463: getfield 267 (Conversion/base64_key Ljava/util/Vector;) 
;              466: ldc_w 279 ("x") 
;              469: invokevirtual 128 (java/util/Vector/addElement (Ljava/lang/Object;)V) 
;              472: aload_0 
;              473: getfield 267 (Conversion/base64_key Ljava/util/Vector;) 
;              476: ldc_w 277 ("y") 
;              479: invokevirtual 128 (java/util/Vector/addElement (Ljava/lang/Object;)V) 
;              482: aload_0 
;              483: getfield 267 (Conversion/base64_key Ljava/util/Vector;) 
;              486: ldc_w 274 ("z") 
;              489: invokevirtual 128 (java/util/Vector/addElement (Ljava/lang/Object;)V) 
;              492: aload_0 
;              493: getfield 267 (Conversion/base64_key Ljava/util/Vector;) 
;              496: ldc 84 ("0") 
;              498: invokevirtual 128 (java/util/Vector/addElement (Ljava/lang/Object;)V) 
;              501: aload_0 
;              502: getfield 267 (Conversion/base64_key Ljava/util/Vector;) 
;              505: ldc 83 ("1") 
;              507: invokevirtual 128 (java/util/Vector/addElement (Ljava/lang/Object;)V) 
;              510: aload_0 
;              511: getfield 267 (Conversion/base64_key Ljava/util/Vector;) 
;              514: ldc 82 ("2") 
;              516: invokevirtual 128 (java/util/Vector/addElement (Ljava/lang/Object;)V) 
;              519: aload_0 
;              520: getfield 267 (Conversion/base64_key Ljava/util/Vector;) 
;              523: ldc 81 ("3") 
;              525: invokevirtual 128 (java/util/Vector/addElement (Ljava/lang/Object;)V) 
;              528: aload_0 
;              529: getfield 267 (Conversion/base64_key Ljava/util/Vector;) 
;              532: ldc 80 ("4") 
;              534: invokevirtual 128 (java/util/Vector/addElement (Ljava/lang/Object;)V) 
;              537: aload_0 
;              538: getfield 267 (Conversion/base64_key Ljava/util/Vector;) 
;              541: ldc 79 ("5") 
;              543: invokevirtual 128 (java/util/Vector/addElement (Ljava/lang/Object;)V) 
;              546: aload_0 
;              547: getfield 267 (Conversion/base64_key Ljava/util/Vector;) 
;              550: ldc 78 ("6") 
;              552: invokevirtual 128 (java/util/Vector/addElement (Ljava/lang/Object;)V) 
;              555: aload_0 
;              556: getfield 267 (Conversion/base64_key Ljava/util/Vector;) 
;              559: ldc 77 ("7") 
;              561: invokevirtual 128 (java/util/Vector/addElement (Ljava/lang/Object;)V) 
;              564: aload_0 
;              565: getfield 267 (Conversion/base64_key Ljava/util/Vector;) 
;              568: ldc 76 ("8") 
;              570: invokevirtual 128 (java/util/Vector/addElement (Ljava/lang/Object;)V) 
;              573: aload_0 
;              574: getfield 267 (Conversion/base64_key Ljava/util/Vector;) 
;              577: ldc 75 ("9") 
;              579: invokevirtual 128 (java/util/Vector/addElement (Ljava/lang/Object;)V) 
;              582: aload_0 
;              583: getfield 267 (Conversion/base64_key Ljava/util/Vector;) 
;              586: ldc 87 ("+") 
;              588: invokevirtual 128 (java/util/Vector/addElement (Ljava/lang/Object;)V) 
;              591: aload_0 
;              592: getfield 267 (Conversion/base64_key Ljava/util/Vector;) 
;              595: ldc 85 ("/") 
;              597: invokevirtual 128 (java/util/Vector/addElement (Ljava/lang/Object;)V) 
;              600: new 149 (java/util/Vector) 
;              603: dup 
;              604: invokespecial 260 (java/util/Vector/<init> ()V) 
;              607: dup 
;              608: aload_0 
;              609: swap 
;              610: putfield 54 (Conversion/base64_to10 Ljava/util/Vector;) 
;              613: pop 
;              614: aload_0 
;              615: getfield 54 (Conversion/base64_to10 Ljava/util/Vector;) 
;              618: ldc 84 ("0") 
;              620: invokevirtual 128 (java/util/Vector/addElement (Ljava/lang/Object;)V) 
;              623: aload_0 
;              624: getfield 54 (Conversion/base64_to10 Ljava/util/Vector;) 
;              627: ldc 84 ("0") 
;              629: invokevirtual 128 (java/util/Vector/addElement (Ljava/lang/Object;)V) 
;              632: aload_0 
;              633: getfield 54 (Conversion/base64_to10 Ljava/util/Vector;) 
;              636: ldc 84 ("0") 
;              638: invokevirtual 128 (java/util/Vector/addElement (Ljava/lang/Object;)V) 
;              641: aload_0 
;              642: getfield 54 (Conversion/base64_to10 Ljava/util/Vector;) 
;              645: ldc 84 ("0") 
;              647: invokevirtual 128 (java/util/Vector/addElement (Ljava/lang/Object;)V) 
;              650: aload_0 
;              651: getfield 54 (Conversion/base64_to10 Ljava/util/Vector;) 
;              654: ldc 84 ("0") 
;              656: invokevirtual 128 (java/util/Vector/addElement (Ljava/lang/Object;)V) 
;              659: aload_0 
;              660: getfield 54 (Conversion/base64_to10 Ljava/util/Vector;) 
;              663: ldc 84 ("0") 
;              665: invokevirtual 128 (java/util/Vector/addElement (Ljava/lang/Object;)V) 
;              668: aload_0 
;              669: getfield 54 (Conversion/base64_to10 Ljava/util/Vector;) 
;              672: ldc 84 ("0") 
;              674: invokevirtual 128 (java/util/Vector/addElement (Ljava/lang/Object;)V) 
;              677: aload_0 
;              678: getfield 54 (Conversion/base64_to10 Ljava/util/Vector;) 
;              681: ldc 84 ("0") 
;              683: invokevirtual 128 (java/util/Vector/addElement (Ljava/lang/Object;)V) 
;              686: aload_0 
;              687: getfield 54 (Conversion/base64_to10 Ljava/util/Vector;) 
;              690: ldc 84 ("0") 
;              692: invokevirtual 128 (java/util/Vector/addElement (Ljava/lang/Object;)V) 
;              695: aload_0 
;              696: getfield 54 (Conversion/base64_to10 Ljava/util/Vector;) 
;              699: ldc 84 ("0") 
;              701: invokevirtual 128 (java/util/Vector/addElement (Ljava/lang/Object;)V) 
;              704: aload_0 
;              705: getfield 54 (Conversion/base64_to10 Ljava/util/Vector;) 
;              708: ldc 84 ("0") 
;              710: invokevirtual 128 (java/util/Vector/addElement (Ljava/lang/Object;)V) 
;              713: aload_0 
;              714: getfield 54 (Conversion/base64_to10 Ljava/util/Vector;) 
;              717: ldc 84 ("0") 
;              719: invokevirtual 128 (java/util/Vector/addElement (Ljava/lang/Object;)V) 
;              722: aload_0 
;              723: getfield 54 (Conversion/base64_to10 Ljava/util/Vector;) 
;              726: ldc 84 ("0") 
;              728: invokevirtual 128 (java/util/Vector/addElement (Ljava/lang/Object;)V) 
;              731: aload_0 
;              732: getfield 54 (Conversion/base64_to10 Ljava/util/Vector;) 
;              735: ldc 84 ("0") 
;              737: invokevirtual 128 (java/util/Vector/addElement (Ljava/lang/Object;)V) 
;              740: aload_0 
;              741: getfield 54 (Conversion/base64_to10 Ljava/util/Vector;) 
;              744: ldc 84 ("0") 
;              746: invokevirtual 128 (java/util/Vector/addElement (Ljava/lang/Object;)V) 
;              749: aload_0 
;              750: getfield 54 (Conversion/base64_to10 Ljava/util/Vector;) 
;              753: ldc 84 ("0") 
;              755: invokevirtual 128 (java/util/Vector/addElement (Ljava/lang/Object;)V) 
;              758: aload_0 
;              759: getfield 54 (Conversion/base64_to10 Ljava/util/Vector;) 
;              762: ldc 84 ("0") 
;              764: invokevirtual 128 (java/util/Vector/addElement (Ljava/lang/Object;)V) 
;              767: aload_0 
;              768: getfield 54 (Conversion/base64_to10 Ljava/util/Vector;) 
;              771: ldc 84 ("0") 
;              773: invokevirtual 128 (java/util/Vector/addElement (Ljava/lang/Object;)V) 
;              776: aload_0 
;              777: getfield 54 (Conversion/base64_to10 Ljava/util/Vector;) 
;              780: ldc 84 ("0") 
;              782: invokevirtual 128 (java/util/Vector/addElement (Ljava/lang/Object;)V) 
;              785: aload_0 
;              786: getfield 54 (Conversion/base64_to10 Ljava/util/Vector;) 
;              789: ldc 84 ("0") 
;              791: invokevirtual 128 (java/util/Vector/addElement (Ljava/lang/Object;)V) 
;              794: aload_0 
;              795: getfield 54 (Conversion/base64_to10 Ljava/util/Vector;) 
;              798: ldc 84 ("0") 
;              800: invokevirtual 128 (java/util/Vector/addElement (Ljava/lang/Object;)V) 
;              803: aload_0 
;              804: getfield 54 (Conversion/base64_to10 Ljava/util/Vector;) 
;              807: ldc 84 ("0") 
;              809: invokevirtual 128 (java/util/Vector/addElement (Ljava/lang/Object;)V) 
;              812: aload_0 
;              813: getfield 54 (Conversion/base64_to10 Ljava/util/Vector;) 
;              816: ldc 84 ("0") 
;              818: invokevirtual 128 (java/util/Vector/addElement (Ljava/lang/Object;)V) 
;              821: aload_0 
;              822: getfield 54 (Conversion/base64_to10 Ljava/util/Vector;) 
;              825: ldc 84 ("0") 
;              827: invokevirtual 128 (java/util/Vector/addElement (Ljava/lang/Object;)V) 
;              830: aload_0 
;              831: getfield 54 (Conversion/base64_to10 Ljava/util/Vector;) 
;              834: ldc 84 ("0") 
;              836: invokevirtual 128 (java/util/Vector/addElement (Ljava/lang/Object;)V) 
;              839: aload_0 
;              840: getfield 54 (Conversion/base64_to10 Ljava/util/Vector;) 
;              843: ldc 84 ("0") 
;              845: invokevirtual 128 (java/util/Vector/addElement (Ljava/lang/Object;)V) 
;              848: aload_0 
;              849: getfield 54 (Conversion/base64_to10 Ljava/util/Vector;) 
;              852: ldc 84 ("0") 
;              854: invokevirtual 128 (java/util/Vector/addElement (Ljava/lang/Object;)V) 
;              857: aload_0 
;              858: getfield 54 (Conversion/base64_to10 Ljava/util/Vector;) 
;              861: ldc 84 ("0") 
;              863: invokevirtual 128 (java/util/Vector/addElement (Ljava/lang/Object;)V) 
;              866: aload_0 
;              867: getfield 54 (Conversion/base64_to10 Ljava/util/Vector;) 
;              870: ldc 84 ("0") 
;              872: invokevirtual 128 (java/util/Vector/addElement (Ljava/lang/Object;)V) 
;              875: aload_0 
;              876: getfield 54 (Conversion/base64_to10 Ljava/util/Vector;) 
;              879: ldc 84 ("0") 
;              881: invokevirtual 128 (java/util/Vector/addElement (Ljava/lang/Object;)V) 
;              884: aload_0 
;              885: getfield 54 (Conversion/base64_to10 Ljava/util/Vector;) 
;              888: ldc 84 ("0") 
;              890: invokevirtual 128 (java/util/Vector/addElement (Ljava/lang/Object;)V) 
;              893: aload_0 
;              894: getfield 54 (Conversion/base64_to10 Ljava/util/Vector;) 
;              897: ldc 84 ("0") 
;              899: invokevirtual 128 (java/util/Vector/addElement (Ljava/lang/Object;)V) 
;              902: aload_0 
;              903: getfield 54 (Conversion/base64_to10 Ljava/util/Vector;) 
;              906: ldc 84 ("0") 
;              908: invokevirtual 128 (java/util/Vector/addElement (Ljava/lang/Object;)V) 
;              911: aload_0 
;              912: getfield 54 (Conversion/base64_to10 Ljava/util/Vector;) 
;              915: ldc 84 ("0") 
;              917: invokevirtual 128 (java/util/Vector/addElement (Ljava/lang/Object;)V) 
;              920: aload_0 
;              921: getfield 54 (Conversion/base64_to10 Ljava/util/Vector;) 
;              924: ldc 84 ("0") 
;              926: invokevirtual 128 (java/util/Vector/addElement (Ljava/lang/Object;)V) 
;              929: aload_0 
;              930: getfield 54 (Conversion/base64_to10 Ljava/util/Vector;) 
;              933: ldc 84 ("0") 
;              935: invokevirtual 128 (java/util/Vector/addElement (Ljava/lang/Object;)V) 
;              938: aload_0 
;              939: getfield 54 (Conversion/base64_to10 Ljava/util/Vector;) 
;              942: ldc 84 ("0") 
;              944: invokevirtual 128 (java/util/Vector/addElement (Ljava/lang/Object;)V) 
;              947: aload_0 
;              948: getfield 54 (Conversion/base64_to10 Ljava/util/Vector;) 
;              951: ldc 84 ("0") 
;              953: invokevirtual 128 (java/util/Vector/addElement (Ljava/lang/Object;)V) 
;              956: aload_0 
;              957: getfield 54 (Conversion/base64_to10 Ljava/util/Vector;) 
;              960: ldc 84 ("0") 
;              962: invokevirtual 128 (java/util/Vector/addElement (Ljava/lang/Object;)V) 
;              965: aload_0 
;              966: getfield 54 (Conversion/base64_to10 Ljava/util/Vector;) 
;              969: ldc 84 ("0") 
;              971: invokevirtual 128 (java/util/Vector/addElement (Ljava/lang/Object;)V) 
;              974: aload_0 
;              975: getfield 54 (Conversion/base64_to10 Ljava/util/Vector;) 
;              978: ldc 84 ("0") 
;              980: invokevirtual 128 (java/util/Vector/addElement (Ljava/lang/Object;)V) 
;              983: aload_0 
;              984: getfield 54 (Conversion/base64_to10 Ljava/util/Vector;) 
;              987: ldc 84 ("0") 
;              989: invokevirtual 128 (java/util/Vector/addElement (Ljava/lang/Object;)V) 
;              992: aload_0 
;              993: getfield 54 (Conversion/base64_to10 Ljava/util/Vector;) 
;              996: ldc 84 ("0") 
;              998: invokevirtual 128 (java/util/Vector/addElement (Ljava/lang/Object;)V) 
;             1001: aload_0 
;             1002: getfield 54 (Conversion/base64_to10 Ljava/util/Vector;) 
;             1005: ldc_w 273 ("62") 
;             1008: invokevirtual 128 (java/util/Vector/addElement (Ljava/lang/Object;)V) 
;             1011: aload_0 
;             1012: getfield 54 (Conversion/base64_to10 Ljava/util/Vector;) 
;             1015: ldc 84 ("0") 
;             1017: invokevirtual 128 (java/util/Vector/addElement (Ljava/lang/Object;)V) 
;             1020: aload_0 
;             1021: getfield 54 (Conversion/base64_to10 Ljava/util/Vector;) 
;             1024: ldc 84 ("0") 
;             1026: invokevirtual 128 (java/util/Vector/addElement (Ljava/lang/Object;)V) 
;             1029: aload_0 
;             1030: getfield 54 (Conversion/base64_to10 Ljava/util/Vector;) 
;             1033: ldc 84 ("0") 
;             1035: invokevirtual 128 (java/util/Vector/addElement (Ljava/lang/Object;)V) 
;             1038: aload_0 
;             1039: getfield 54 (Conversion/base64_to10 Ljava/util/Vector;) 
;             1042: ldc_w 272 ("63") 
;             1045: invokevirtual 128 (java/util/Vector/addElement (Ljava/lang/Object;)V) 
;             1048: aload_0 
;             1049: getfield 54 (Conversion/base64_to10 Ljava/util/Vector;) 
;             1052: ldc 32 ("52") 
;             1054: invokevirtual 128 (java/util/Vector/addElement (Ljava/lang/Object;)V) 
;             1057: aload_0 
;             1058: getfield 54 (Conversion/base64_to10 Ljava/util/Vector;) 
;             1061: ldc 31 ("53") 
;             1063: invokevirtual 128 (java/util/Vector/addElement (Ljava/lang/Object;)V) 
;             1066: aload_0 
;             1067: getfield 54 (Conversion/base64_to10 Ljava/util/Vector;) 
;             1070: ldc 30 ("54") 
;             1072: invokevirtual 128 (java/util/Vector/addElement (Ljava/lang/Object;)V) 
;             1075: aload_0 
;             1076: getfield 54 (Conversion/base64_to10 Ljava/util/Vector;) 
;             1079: ldc 29 ("55") 
;             1081: invokevirtual 128 (java/util/Vector/addElement (Ljava/lang/Object;)V) 
;             1084: aload_0 
;             1085: getfield 54 (Conversion/base64_to10 Ljava/util/Vector;) 
;             1088: ldc 28 ("56") 
;             1090: invokevirtual 128 (java/util/Vector/addElement (Ljava/lang/Object;)V) 
;             1093: aload_0 
;             1094: getfield 54 (Conversion/base64_to10 Ljava/util/Vector;) 
;             1097: ldc 27 ("57") 
;             1099: invokevirtual 128 (java/util/Vector/addElement (Ljava/lang/Object;)V) 
;             1102: aload_0 
;             1103: getfield 54 (Conversion/base64_to10 Ljava/util/Vector;) 
;             1106: ldc 25 ("58") 
;             1108: invokevirtual 128 (java/util/Vector/addElement (Ljava/lang/Object;)V) 
;             1111: aload_0 
;             1112: getfield 54 (Conversion/base64_to10 Ljava/util/Vector;) 
;             1115: ldc 23 ("59") 
;             1117: invokevirtual 128 (java/util/Vector/addElement (Ljava/lang/Object;)V) 
;             1120: aload_0 
;             1121: getfield 54 (Conversion/base64_to10 Ljava/util/Vector;) 
;             1124: ldc_w 278 ("60") 
;             1127: invokevirtual 128 (java/util/Vector/addElement (Ljava/lang/Object;)V) 
;             1130: aload_0 
;             1131: getfield 54 (Conversion/base64_to10 Ljava/util/Vector;) 
;             1134: ldc_w 275 ("61") 
;             1137: invokevirtual 128 (java/util/Vector/addElement (Ljava/lang/Object;)V) 
;             1140: aload_0 
;             1141: getfield 54 (Conversion/base64_to10 Ljava/util/Vector;) 
;             1144: ldc 84 ("0") 
;             1146: invokevirtual 128 (java/util/Vector/addElement (Ljava/lang/Object;)V) 
;             1149: aload_0 
;             1150: getfield 54 (Conversion/base64_to10 Ljava/util/Vector;) 
;             1153: ldc 84 ("0") 
;             1155: invokevirtual 128 (java/util/Vector/addElement (Ljava/lang/Object;)V) 
;             1158: aload_0 
;             1159: getfield 54 (Conversion/base64_to10 Ljava/util/Vector;) 
;             1162: ldc 84 ("0") 
;             1164: invokevirtual 128 (java/util/Vector/addElement (Ljava/lang/Object;)V) 
;             1167: aload_0 
;             1168: getfield 54 (Conversion/base64_to10 Ljava/util/Vector;) 
;             1171: ldc 84 ("0") 
;             1173: invokevirtual 128 (java/util/Vector/addElement (Ljava/lang/Object;)V) 
;             1176: aload_0 
;             1177: getfield 54 (Conversion/base64_to10 Ljava/util/Vector;) 
;             1180: ldc 84 ("0") 
;             1182: invokevirtual 128 (java/util/Vector/addElement (Ljava/lang/Object;)V) 
;             1185: aload_0 
;             1186: getfield 54 (Conversion/base64_to10 Ljava/util/Vector;) 
;             1189: ldc 84 ("0") 
;             1191: invokevirtual 128 (java/util/Vector/addElement (Ljava/lang/Object;)V) 
;             1194: aload_0 
;             1195: getfield 54 (Conversion/base64_to10 Ljava/util/Vector;) 
;             1198: ldc 84 ("0") 
;             1200: invokevirtual 128 (java/util/Vector/addElement (Ljava/lang/Object;)V) 
;             1203: aload_0 
;             1204: getfield 54 (Conversion/base64_to10 Ljava/util/Vector;) 
;             1207: ldc 84 ("0") 
;             1209: invokevirtual 128 (java/util/Vector/addElement (Ljava/lang/Object;)V) 
;             1212: aload_0 
;             1213: getfield 54 (Conversion/base64_to10 Ljava/util/Vector;) 
;             1216: ldc 83 ("1") 
;             1218: invokevirtual 128 (java/util/Vector/addElement (Ljava/lang/Object;)V) 
;             1221: aload_0 
;             1222: getfield 54 (Conversion/base64_to10 Ljava/util/Vector;) 
;             1225: ldc 82 ("2") 
;             1227: invokevirtual 128 (java/util/Vector/addElement (Ljava/lang/Object;)V) 
;             1230: aload_0 
;             1231: getfield 54 (Conversion/base64_to10 Ljava/util/Vector;) 
;             1234: ldc 81 ("3") 
;             1236: invokevirtual 128 (java/util/Vector/addElement (Ljava/lang/Object;)V) 
;             1239: aload_0 
;             1240: getfield 54 (Conversion/base64_to10 Ljava/util/Vector;) 
;             1243: ldc 80 ("4") 
;             1245: invokevirtual 128 (java/util/Vector/addElement (Ljava/lang/Object;)V) 
;             1248: aload_0 
;             1249: getfield 54 (Conversion/base64_to10 Ljava/util/Vector;) 
;             1252: ldc 79 ("5") 
;             1254: invokevirtual 128 (java/util/Vector/addElement (Ljava/lang/Object;)V) 
;             1257: aload_0 
;             1258: getfield 54 (Conversion/base64_to10 Ljava/util/Vector;) 
;             1261: ldc 78 ("6") 
;             1263: invokevirtual 128 (java/util/Vector/addElement (Ljava/lang/Object;)V) 
;             1266: aload_0 
;             1267: getfield 54 (Conversion/base64_to10 Ljava/util/Vector;) 
;             1270: ldc 77 ("7") 
;             1272: invokevirtual 128 (java/util/Vector/addElement (Ljava/lang/Object;)V) 
;             1275: aload_0 
;             1276: getfield 54 (Conversion/base64_to10 Ljava/util/Vector;) 
;             1279: ldc 76 ("8") 
;             1281: invokevirtual 128 (java/util/Vector/addElement (Ljava/lang/Object;)V) 
;             1284: aload_0 
;             1285: getfield 54 (Conversion/base64_to10 Ljava/util/Vector;) 
;             1288: ldc 75 ("9") 
;             1290: invokevirtual 128 (java/util/Vector/addElement (Ljava/lang/Object;)V) 
;             1293: aload_0 
;             1294: getfield 54 (Conversion/base64_to10 Ljava/util/Vector;) 
;             1297: ldc 125 ("10") 
;             1299: invokevirtual 128 (java/util/Vector/addElement (Ljava/lang/Object;)V) 
;             1302: aload_0 
;             1303: getfield 54 (Conversion/base64_to10 Ljava/util/Vector;) 
;             1306: ldc 124 ("11") 
;             1308: invokevirtual 128 (java/util/Vector/addElement (Ljava/lang/Object;)V) 
;             1311: aload_0 
;             1312: getfield 54 (Conversion/base64_to10 Ljava/util/Vector;) 
;             1315: ldc 123 ("12") 
;             1317: invokevirtual 128 (java/util/Vector/addElement (Ljava/lang/Object;)V) 
;             1320: aload_0 
;             1321: getfield 54 (Conversion/base64_to10 Ljava/util/Vector;) 
;             1324: ldc 122 ("13") 
;             1326: invokevirtual 128 (java/util/Vector/addElement (Ljava/lang/Object;)V) 
;             1329: aload_0 
;             1330: getfield 54 (Conversion/base64_to10 Ljava/util/Vector;) 
;             1333: ldc 121 ("14") 
;             1335: invokevirtual 128 (java/util/Vector/addElement (Ljava/lang/Object;)V) 
;             1338: aload_0 
;             1339: getfield 54 (Conversion/base64_to10 Ljava/util/Vector;) 
;             1342: ldc 120 ("15") 
;             1344: invokevirtual 128 (java/util/Vector/addElement (Ljava/lang/Object;)V) 
;             1347: aload_0 
;             1348: getfield 54 (Conversion/base64_to10 Ljava/util/Vector;) 
;             1351: ldc 119 ("16") 
;             1353: invokevirtual 128 (java/util/Vector/addElement (Ljava/lang/Object;)V) 
;             1356: aload_0 
;             1357: getfield 54 (Conversion/base64_to10 Ljava/util/Vector;) 
;             1360: ldc 118 ("17") 
;             1362: invokevirtual 128 (java/util/Vector/addElement (Ljava/lang/Object;)V) 
;             1365: aload_0 
;             1366: getfield 54 (Conversion/base64_to10 Ljava/util/Vector;) 
;             1369: ldc 117 ("18") 
;             1371: invokevirtual 128 (java/util/Vector/addElement (Ljava/lang/Object;)V) 
;             1374: aload_0 
;             1375: getfield 54 (Conversion/base64_to10 Ljava/util/Vector;) 
;             1378: ldc 116 ("19") 
;             1380: invokevirtual 128 (java/util/Vector/addElement (Ljava/lang/Object;)V) 
;             1383: aload_0 
;             1384: getfield 54 (Conversion/base64_to10 Ljava/util/Vector;) 
;             1387: ldc 112 ("20") 
;             1389: invokevirtual 128 (java/util/Vector/addElement (Ljava/lang/Object;)V) 
;             1392: aload_0 
;             1393: getfield 54 (Conversion/base64_to10 Ljava/util/Vector;) 
;             1396: ldc 111 ("21") 
;             1398: invokevirtual 128 (java/util/Vector/addElement (Ljava/lang/Object;)V) 
;             1401: aload_0 
;             1402: getfield 54 (Conversion/base64_to10 Ljava/util/Vector;) 
;             1405: ldc 109 ("22") 
;             1407: invokevirtual 128 (java/util/Vector/addElement (Ljava/lang/Object;)V) 
;             1410: aload_0 
;             1411: getfield 54 (Conversion/base64_to10 Ljava/util/Vector;) 
;             1414: ldc 108 ("23") 
;             1416: invokevirtual 128 (java/util/Vector/addElement (Ljava/lang/Object;)V) 
;             1419: aload_0 
;             1420: getfield 54 (Conversion/base64_to10 Ljava/util/Vector;) 
;             1423: ldc 107 ("24") 
;             1425: invokevirtual 128 (java/util/Vector/addElement (Ljava/lang/Object;)V) 
;             1428: aload_0 
;             1429: getfield 54 (Conversion/base64_to10 Ljava/util/Vector;) 
;             1432: ldc 106 ("25") 
;             1434: invokevirtual 128 (java/util/Vector/addElement (Ljava/lang/Object;)V) 
;             1437: aload_0 
;             1438: getfield 54 (Conversion/base64_to10 Ljava/util/Vector;) 
;             1441: ldc 84 ("0") 
;             1443: invokevirtual 128 (java/util/Vector/addElement (Ljava/lang/Object;)V) 
;             1446: aload_0 
;             1447: getfield 54 (Conversion/base64_to10 Ljava/util/Vector;) 
;             1450: ldc 84 ("0") 
;             1452: invokevirtual 128 (java/util/Vector/addElement (Ljava/lang/Object;)V) 
;             1455: aload_0 
;             1456: getfield 54 (Conversion/base64_to10 Ljava/util/Vector;) 
;             1459: ldc 84 ("0") 
;             1461: invokevirtual 128 (java/util/Vector/addElement (Ljava/lang/Object;)V) 
;             1464: aload_0 
;             1465: getfield 54 (Conversion/base64_to10 Ljava/util/Vector;) 
;             1468: ldc 84 ("0") 
;             1470: invokevirtual 128 (java/util/Vector/addElement (Ljava/lang/Object;)V) 
;             1473: aload_0 
;             1474: getfield 54 (Conversion/base64_to10 Ljava/util/Vector;) 
;             1477: ldc 84 ("0") 
;             1479: invokevirtual 128 (java/util/Vector/addElement (Ljava/lang/Object;)V) 
;             1482: aload_0 
;             1483: getfield 54 (Conversion/base64_to10 Ljava/util/Vector;) 
;             1486: ldc 84 ("0") 
;             1488: invokevirtual 128 (java/util/Vector/addElement (Ljava/lang/Object;)V) 
;             1491: aload_0 
;             1492: getfield 54 (Conversion/base64_to10 Ljava/util/Vector;) 
;             1495: ldc 105 ("26") 
;             1497: invokevirtual 128 (java/util/Vector/addElement (Ljava/lang/Object;)V) 
;             1500: aload_0 
;             1501: getfield 54 (Conversion/base64_to10 Ljava/util/Vector;) 
;             1504: ldc 104 ("27") 
;             1506: invokevirtual 128 (java/util/Vector/addElement (Ljava/lang/Object;)V) 
;             1509: aload_0 
;             1510: getfield 54 (Conversion/base64_to10 Ljava/util/Vector;) 
;             1513: ldc 103 ("28") 
;             1515: invokevirtual 128 (java/util/Vector/addElement (Ljava/lang/Object;)V) 
;             1518: aload_0 
;             1519: getfield 54 (Conversion/base64_to10 Ljava/util/Vector;) 
;             1522: ldc 101 ("29") 
;             1524: invokevirtual 128 (java/util/Vector/addElement (Ljava/lang/Object;)V) 
;             1527: aload_0 
;             1528: getfield 54 (Conversion/base64_to10 Ljava/util/Vector;) 
;             1531: ldc 98 ("30") 
;             1533: invokevirtual 128 (java/util/Vector/addElement (Ljava/lang/Object;)V) 
;             1536: aload_0 
;             1537: getfield 54 (Conversion/base64_to10 Ljava/util/Vector;) 
;             1540: ldc 97 ("31") 
;             1542: invokevirtual 128 (java/util/Vector/addElement (Ljava/lang/Object;)V) 
;             1545: aload_0 
;             1546: getfield 54 (Conversion/base64_to10 Ljava/util/Vector;) 
;             1549: ldc 96 ("32") 
;             1551: invokevirtual 128 (java/util/Vector/addElement (Ljava/lang/Object;)V) 
;             1554: aload_0 
;             1555: getfield 54 (Conversion/base64_to10 Ljava/util/Vector;) 
;             1558: ldc 95 ("33") 
;             1560: invokevirtual 128 (java/util/Vector/addElement (Ljava/lang/Object;)V) 
;             1563: aload_0 
;             1564: getfield 54 (Conversion/base64_to10 Ljava/util/Vector;) 
;             1567: ldc 94 ("34") 
;             1569: invokevirtual 128 (java/util/Vector/addElement (Ljava/lang/Object;)V) 
;             1572: aload_0 
;             1573: getfield 54 (Conversion/base64_to10 Ljava/util/Vector;) 
;             1576: ldc 93 ("35") 
;             1578: invokevirtual 128 (java/util/Vector/addElement (Ljava/lang/Object;)V) 
;             1581: aload_0 
;             1582: getfield 54 (Conversion/base64_to10 Ljava/util/Vector;) 
;             1585: ldc 92 ("36") 
;             1587: invokevirtual 128 (java/util/Vector/addElement (Ljava/lang/Object;)V) 
;             1590: aload_0 
;             1591: getfield 54 (Conversion/base64_to10 Ljava/util/Vector;) 
;             1594: ldc 91 ("37") 
;             1596: invokevirtual 128 (java/util/Vector/addElement (Ljava/lang/Object;)V) 
;             1599: aload_0 
;             1600: getfield 54 (Conversion/base64_to10 Ljava/util/Vector;) 
;             1603: ldc 90 ("38") 
;             1605: invokevirtual 128 (java/util/Vector/addElement (Ljava/lang/Object;)V) 
;             1608: aload_0 
;             1609: getfield 54 (Conversion/base64_to10 Ljava/util/Vector;) 
;             1612: ldc 89 ("39") 
;             1614: invokevirtual 128 (java/util/Vector/addElement (Ljava/lang/Object;)V) 
;             1617: aload_0 
;             1618: getfield 54 (Conversion/base64_to10 Ljava/util/Vector;) 
;             1621: ldc 74 ("40") 
;             1623: invokevirtual 128 (java/util/Vector/addElement (Ljava/lang/Object;)V) 
;             1626: aload_0 
;             1627: getfield 54 (Conversion/base64_to10 Ljava/util/Vector;) 
;             1630: ldc 73 ("41") 
;             1632: invokevirtual 128 (java/util/Vector/addElement (Ljava/lang/Object;)V) 
;             1635: aload_0 
;             1636: getfield 54 (Conversion/base64_to10 Ljava/util/Vector;) 
;             1639: ldc 72 ("42") 
;             1641: invokevirtual 128 (java/util/Vector/addElement (Ljava/lang/Object;)V) 
;             1644: aload_0 
;             1645: getfield 54 (Conversion/base64_to10 Ljava/util/Vector;) 
;             1648: ldc 71 ("43") 
;             1650: invokevirtual 128 (java/util/Vector/addElement (Ljava/lang/Object;)V) 
;             1653: aload_0 
;             1654: getfield 54 (Conversion/base64_to10 Ljava/util/Vector;) 
;             1657: ldc 70 ("44") 
;             1659: invokevirtual 128 (java/util/Vector/addElement (Ljava/lang/Object;)V) 
;             1662: aload_0 
;             1663: getfield 54 (Conversion/base64_to10 Ljava/util/Vector;) 
;             1666: ldc 69 ("45") 
;             1668: invokevirtual 128 (java/util/Vector/addElement (Ljava/lang/Object;)V) 
;             1671: aload_0 
;             1672: getfield 54 (Conversion/base64_to10 Ljava/util/Vector;) 
;             1675: ldc 68 ("46") 
;             1677: invokevirtual 128 (java/util/Vector/addElement (Ljava/lang/Object;)V) 
;             1680: aload_0 
;             1681: getfield 54 (Conversion/base64_to10 Ljava/util/Vector;) 
;             1684: ldc 66 ("47") 
;             1686: invokevirtual 128 (java/util/Vector/addElement (Ljava/lang/Object;)V) 
;             1689: aload_0 
;             1690: getfield 54 (Conversion/base64_to10 Ljava/util/Vector;) 
;             1693: ldc 64 ("48") 
;             1695: invokevirtual 128 (java/util/Vector/addElement (Ljava/lang/Object;)V) 
;             1698: aload_0 
;             1699: getfield 54 (Conversion/base64_to10 Ljava/util/Vector;) 
;             1702: ldc 62 ("49") 
;             1704: invokevirtual 128 (java/util/Vector/addElement (Ljava/lang/Object;)V) 
;             1707: aload_0 
;             1708: getfield 54 (Conversion/base64_to10 Ljava/util/Vector;) 
;             1711: ldc 35 ("50") 
;             1713: invokevirtual 128 (java/util/Vector/addElement (Ljava/lang/Object;)V) 
;             1716: aload_0 
;             1717: getfield 54 (Conversion/base64_to10 Ljava/util/Vector;) 
;             1720: ldc 33 ("51") 
;             1722: invokevirtual 128 (java/util/Vector/addElement (Ljava/lang/Object;)V) 
;             1725: return 
;         exception_table_length 0
;         attributes_count 0


; methods[1] (offset 0xc20) :
;     access_flags 0x1 [ ACC_PUBLIC ]
;     name_index 99 (get64)
;     descriptor_index 3 ((I)C)
;     attributes_count 1
;     method_attributes[0] :
;         name_index 153 (Code)
;         attribute_length 33
;         max_stack 2
;         max_locals 3
;         code_length 21
;         code :
;                0: aload_0 
;                1: getfield 267 (Conversion/base64_key Ljava/util/Vector;) 
;                4: iload_1 
;                5: invokevirtual 100 (java/util/Vector/elementAt (I)Ljava/lang/Object;) 
;                8: checkcast 51 (java/lang/String) 
;               11: dup 
;               12: astore_2 
;               13: pop 
;               14: aload_2 
;               15: iconst_0 
;               16: invokevirtual 202 (java/lang/String/charAt (I)C) 
;               19: ireturn 
;               20: nop 
;         exception_table_length 0
;         attributes_count 0


; methods[2] (offset 0xc4f) :
;     access_flags 0x1 [ ACC_PUBLIC ]
;     name_index 166 (get10)
;     descriptor_index 3 ((I)C)
;     attributes_count 1
;     method_attributes[0] :
;         name_index 153 (Code)
;         attribute_length 40
;         max_stack 4
;         max_locals 3
;         code_length 28
;         code :
;                0: new 176 (java/lang/Integer) 
;                3: dup 
;                4: aload_0 
;                5: getfield 54 (Conversion/base64_to10 Ljava/util/Vector;) 
;                8: iload_1 
;                9: invokevirtual 100 (java/util/Vector/elementAt (I)Ljava/lang/Object;) 
;               12: checkcast 51 (java/lang/String) 
;               15: invokespecial 115 (java/lang/Integer/<init> (Ljava/lang/String;)V) 
;               18: dup 
;               19: astore_2 
;               20: pop 
;               21: aload_2 
;               22: invokevirtual 205 (java/lang/Integer/intValue ()I) 
;               25: i2c 
;               26: ireturn 
;               27: nop 
;         exception_table_length 0
;         attributes_count 0



; attributes_count 1

; class_attributes[0] (offset 0xc87) :
;     name_index 201 (SourceFile)
;     attribute_length 2
;     sourcefile_index 126

; End of file reached successfully. Enjoy :)
